{"id": "01945990-d86e-7293-b360-4d5791bdfc0c", "name": null, "timestamp": "2025-01-12T13:40:52.398629", "metadata": {"test_presets": ["DataDriftTestPreset"]}, "tags": [], "suite": {"metrics": [{"type": "evidently:metric:DataDriftTable", "options": {"color": null, "render": null, "data_definition": null}, "stattest": null, "cat_stattest": null, "num_stattest": null, "text_stattest": null, "per_column_stattest": null, "stattest_threshold": null, "cat_stattest_threshold": null, "num_stattest_threshold": null, "text_stattest_threshold": null, "per_column_stattest_threshold": null, "columns": null, "feature_importance": false}, {"type": "evidently:metric:ColumnDriftMetric", "options": {"color": null, "render": null, "data_definition": null}, "column_name": {"type": "evidently:base:ColumnName", "name": "mainroad", "display_name": "mainroad", "dataset": "main"}, "stattest": null, "stattest_threshold": null}, {"type": "evidently:metric:ColumnDriftMetric", "options": {"color": null, "render": null, "data_definition": null}, "column_name": {"type": "evidently:base:ColumnName", "name": "house_id", "display_name": "house_id", "dataset": "main"}, "stattest": null, "stattest_threshold": null}, {"type": "evidently:metric:ColumnDriftMetric", "options": {"color": null, "render": null, "data_definition": null}, "column_name": {"type": "evidently:base:ColumnName", "name": "area", "display_name": "area", "dataset": "main"}, "stattest": null, "stattest_threshold": null}, {"type": "evidently:metric:ColumnDriftMetric", "options": {"color": null, "render": null, "data_definition": null}, "column_name": {"type": "evidently:base:ColumnName", "name": "bedrooms", "display_name": "bedrooms", "dataset": "main"}, "stattest": null, "stattest_threshold": null}], "metric_results": [{"type": "evidently:metric_result:DataDriftTableResults", "number_of_columns": 4, "number_of_drifted_columns": 3, "share_of_drifted_columns": 0.75, "dataset_drift": true, "drift_by_columns": {"area": {"type": "evidently:metric_result:ColumnDataDriftMetrics", "column_name": "area", "column_type": "num", "stattest_name": "K-S p_value", "stattest_threshold": 0.05, "drift_score": 0.03958772716902705, "drift_detected": true, "current": {"type": "evidently:metric_result:DriftStatsField", "distribution": {"type": "evidently:metric_result:Distribution", "x": [-1.6145297288894653, -1.1951051577925682, -0.7756805866956711, -0.35625601559877396, 0.06316855549812317, 0.4825931265950203, 0.9020176976919174, 1.3214422687888145, 1.7408668398857117, 2.160291410982609, 2.579715982079506, 2.999140553176403, 3.4185651242733, 3.8379896953701973, 4.257414266467094, 4.6768388375639915, 5.096263408660889], "y": [28, 86, 135, 69, 78, 65, 86, 23, 10, 9, 4, 1, 4, 0, 0, 2]}, "characteristic_examples": null, "characteristic_words": null, "small_distribution": {"type": "evidently:metric_result:DistributionIncluded", "x": [-1.6145297288894653, -0.94345041513443, -0.2723711013793946, 0.3987082123756407, 1.0697875261306762, 1.7408668398857117, 2.4119461536407467, 3.0830254673957826, 3.7541047811508177, 4.425184094905853, 5.096263408660889], "y": [0.1812999807517219, 0.4942287146519542, 0.28809312009862664, 0.21855340145413046, 0.2334547697350939, 0.037253420702408634, 0.019868491041284575, 0.012417806900802878, 0.0, 0.004967122760321144]}, "correlations": {"area": 1.0, "bedrooms": 0.2408715105561196, "house_id": -0.2546058857142971, "mainroad": 0.4480668891787448}}, "reference": {"type": "evidently:metric_result:DriftStatsField", "distribution": {"type": "evidently:metric_result:Distribution", "x": [-1.6145297288894653, -1.1951051577925682, -0.7756805866956711, -0.35625601559877396, 0.06316855549812317, 0.4825931265950203, 0.9020176976919174, 1.3214422687888145, 1.7408668398857117, 2.160291410982609, 2.579715982079506, 2.999140553176403, 3.4185651242733, 3.8379896953701973, 4.257414266467094, 4.6768388375639915, 5.096263408660889], "y": [28, 86, 135, 69, 78, 65, 31, 23, 10, 9, 4, 1, 4, 0, 0, 2]}, "characteristic_examples": null, "characteristic_words": null, "small_distribution": {"type": "evidently:metric_result:DistributionIncluded", "x": [-1.6145297288894653, -0.94345041513443, -0.2723711013793946, 0.3987082123756407, 1.0697875261306762, 1.7408668398857117, 2.4119461536407467, 3.0830254673957826, 3.7541047811508177, 4.425184094905853, 5.096263408660889], "y": [0.1995963090844645, 0.5441050069562798, 0.3171667377232587, 0.2406092493072996, 0.10663364457937141, 0.04101294022283519, 0.021873568118845405, 0.013670980074278397, 0.0, 0.005468392029711351]}, "correlations": {"area": 1.0, "bedrooms": 0.15185848440562338, "house_id": -0.5414678104835223, "mainroad": 0.2888741122781702}}, "scatter": {"type": "evidently:metric_result:ScatterAggField", "scatter": {"current (mean)": {"per": {"0": 0, "1": 1, "2": 2, "3": 3, "4": 4, "5": 5, "6": 6, "7": 7, "8": 8, "9": 9, "10": 10, "11": 11, "12": 12, "13": 13, "14": 14, "15": 15, "16": 16, "17": 17, "18": 18, "19": 19, "20": 20, "21": 21, "22": 22, "23": 23, "24": 24, "25": 25, "26": 26, "27": 27, "28": 28, "29": 29, "30": 30, "31": 31, "32": 32, "33": 33, "34": 34, "35": 35, "36": 36, "37": 37, "38": 38, "39": 39, "40": 40, "41": 41, "42": 42, "43": 43, "44": 44, "45": 45, "46": 46, "47": 47, "48": 48, "49": 49, "50": 50, "51": 51, "52": 52, "53": 53, "54": 54, "55": 55, "56": 56, "57": 57, "58": 58, "59": 59, "60": 60, "61": 61, "62": 62, "63": 63, "64": 64, "65": 65, "66": 66, "67": 67, "68": 68, "69": 69, "70": 70, "71": 71, "72": 72, "73": 73, "74": 74, "75": 75, "76": 76, "77": 77, "78": 78, "79": 79, "80": 80, "81": 81, "82": 82, "83": 83, "84": 84, "85": 85, "86": 86, "87": 87, "88": 88, "89": 89, "90": 90, "91": 91, "92": 92, "93": 93, "94": 94, "95": 95, "96": 96, "97": 97, "98": 98, "99": 99, "100": 100, "101": 101, "102": 102, "103": 103, "104": 104, "105": 105, "106": 106, "107": 107, "108": 108, "109": 109, "110": 110, "111": 111, "112": 112, "113": 113, "114": 114, "115": 115, "116": 116, "117": 117, "118": 118, "119": 119, "120": 120, "121": 121, "122": 122, "123": 123, "124": 124, "125": 125, "126": 126, "127": 127, "128": 128, "129": 129, "130": 130, "131": 131, "132": 132, "133": 133, "134": 134, "135": 135, "136": 136, "137": 137, "138": 138, "139": 139, "140": 140, "141": 141, "142": 142, "143": 143, "144": 144, "145": 145, "146": 146, "147": 147, "148": 148, "149": 149}, "mean": {"0": 1.526398092508316, "1": 2.2020896673202515, "2": 1.4353065639734268, "3": 0.37449392676353455, "4": 0.6362379342317581, "5": 0.4015907943248749, "6": 1.1084148436784744, "7": 0.8443647623062134, "8": 0.47019768320024014, "9": 0.9085900485515594, "10": 0.5520647466182709, "11": 0.46097323298454285, "12": 0.5653249174356461, "13": 0.2937799322899082, "14": 1.5586836636066437, "15": 0.7930537164211273, "16": 2.3467982709407806, "17": 0.863390177488327, "18": -0.07865753211081028, "19": 0.4632793441414833, "20": 0.680054098367691, "21": 0.23497401177883148, "22": 0.823033170774579, "23": 0.1727089285850525, "24": 0.8530126810073853, "25": 0.38602451980113983, "26": 0.14618860557675362, "27": 0.48714764416217804, "28": 0.9360328018665314, "29": 0.3964020162820816, "30": 0.7774874269962311, "31": 1.7506677359342575, "32": 0.8055067509412766, "33": 0.2764840768650174, "34": 0.09199492447078228, "35": 0.8253393173217773, "36": 0.5878095235675573, "37": 0.21836999827064574, "38": -0.24815694987773895, "39": 0.028230875730514526, "40": 0.591845229268074, "41": 0.5716667175292969, "42": 0.6880101636052132, "43": 0.7722986917942762, "44": 0.4880700707435608, "45": 0.2868615984916687, "46": 0.33528997749090195, "47": 0.8022781908512115, "48": 0.38717758655548096, "49": 0.0036707445979118347, "50": -0.28447825461626053, "51": -0.08442282676696777, "52": 0.7649190947413445, "53": -0.4239981770515442, "54": 0.4744639992713928, "55": 0.7385141104459763, "56": 0.8357168470975012, "57": 0.2784442752599716, "58": -0.3617330864071846, "59": -0.4856867343187332, "60": -0.7854816168546677, "61": 0.2303617838770151, "62": -0.5248906798660755, "63": 0.3658460006117821, "64": 0.2361270636320114, "65": -0.7162981778383255, "66": -0.34847292862832546, "67": -0.6165587101131678, "68": -0.2934721112251282, "69": 0.4517487958073616, "70": -0.3698045015335083, "71": 0.2426994889974594, "72": -0.4784224918112159, "73": -0.8209957629442215, "74": 0.05048486590385437, "75": -0.7331328094005585, "76": 0.0020564422011375427, "77": 0.013932950794696808, "78": -0.42457469180226326, "79": -0.27329360134899616, "80": -0.4372583329677582, "81": -0.237779438495636, "82": -0.09595340490341187, "83": -0.5760864168405533, "84": -0.3940186947584152, "85": -0.102641137316823, "86": -1.0621000528335571, "87": -0.6471147425472736, "88": 0.5458382368087769, "89": -0.469543918967247, "90": -0.335328072309494, "91": -0.550257932394743, "92": -0.40497272461652756, "93": -0.5698599144816399, "94": -0.9025169312953949, "95": -0.5133601129055023, "96": -0.5041356533765793, "97": -0.8280293941497803, "98": -0.24308347702026367, "99": -0.06828003376722336, "100": 1.2953254356980324, "101": -0.5969567578285933, "102": -0.8558180928230286, "103": -0.8321804329752922, "104": -0.5825435556471348, "105": -0.49145202711224556, "106": -1.0921948105096817, "107": -0.7041910737752914, "108": -0.37245650589466095, "109": -0.4781918600201607, "110": -0.6443474292755127, "111": -0.7548102885484695, "112": -0.5369977876543999, "113": 0.16855792701244354, "114": -0.9056301862001419, "115": -0.26429973915219307, "116": -0.6886247992515564, "117": -0.5005611795932055, "118": -0.18104901909828186, "119": -0.29197312518954277, "120": -0.5369977653026581, "121": -0.29197312146425247, "122": -0.5894618732854724, "123": -0.368074893951416, "124": -0.8115407079458237, "125": -0.9100117683410645, "126": -0.7964356392621994, "127": -0.754349060356617, "128": -0.8062366470694542, "129": -0.694390095770359, "130": -0.4618184417486191, "131": -1.0011033117771149, "132": -0.6240536142140627, "133": -1.0195522457361221, "134": -1.0196675211191177, "135": -0.9999502450227737, "136": 0.8184209614992142, "137": 1.2911744117736816, "138": 1.2911744117736816, "139": 1.2911744117736816, "140": 1.2911744117736816, "141": 1.2911744117736816, "142": 1.2911744117736816, "143": 1.2911744117736816, "144": 1.2911744117736816, "145": 1.2911744117736816, "146": 1.2911744117736816, "147": 1.2911744117736816, "148": 1.2911744117736816, "149": 1.2911744117736816}, "std": {"0": 0.5650811431245503, "1": 1.944813528886386, "2": 1.5940989625255135, "3": 0.8330522381839394, "4": 0.7352033543658859, "5": 0.8600176069318263, "6": 0.691355968180247, "7": 0.4893253004392497, "8": 0.44922887398733136, "9": 0.6616709742689956, "10": 0.11281119632680482, "11": 0.13836687803268433, "12": 0.6828886649419398, "13": 0.19601972335658502, "14": 1.0588857431958296, "15": 0.6218817234305231, "16": 1.1277824397231633, "17": 1.6177043116425898, "18": 0.5344350758955237, "19": 0.17263541578913144, "20": 1.2683629393577576, "21": 1.0044427415918111, "22": 0.6897865178623054, "23": 0.6294467276732783, "24": 0.6256331643056557, "25": 0.26386290899208925, "26": 0.36166805457894596, "27": 0.9896151875140321, "28": 1.0335509783737786, "29": 0.7202760027186172, "30": 0.24063591706107518, "31": 2.0507511969155745, "32": 1.4169066745637668, "33": 0.4479643315331358, "34": 0.34196911199411373, "35": 1.1493985219930787, "36": 1.2621983180066627, "37": 0.47862048594565887, "38": 0.6234688750926963, "39": 1.205638050233138, "40": 0.15576519820057388, "41": 0.6129349397242922, "42": 1.195140525320073, "43": 1.2717128798182302, "44": 1.0418676182717002, "45": 1.0003141930164727, "46": 1.8298030888750467, "47": 1.3992522437715402, "48": 0.7966482352603207, "49": 0.9781409034083727, "50": 0.2810898712691035, "51": 0.6725358867350345, "52": 2.002024121088792, "53": 0.29897998487223854, "54": 0.4627843035679054, "55": 1.1586547137438932, "56": 1.036622630820405, "57": 1.2491285226926208, "58": 0.4117447625106459, "59": 0.4226401550957049, "60": 0.2785566026852213, "61": 0.9336165819360146, "62": 0.3296022996344721, "63": 1.2845607367816436, "64": 0.9444028675890677, "65": 0.1592929203002804, "66": 0.4658959941011283, "67": 0.6195265652532779, "68": 0.6073061846290396, "69": 1.4188783484610112, "70": 0.7896354463683246, "71": 0.9860109367505998, "72": 0.7283383036247912, "73": 0.45803348070795524, "74": 0.6725635564757445, "75": 0.4731212994124878, "76": 0.9870923815066247, "77": 0.4618898393702745, "78": 0.4303978078793738, "79": 0.5626294166082602, "80": 0.4061970264982373, "81": 0.6007180771902371, "82": 0.7208701074072844, "83": 0.5156042056729633, "84": 1.2044061686509806, "85": 0.7925865139529534, "86": 0.41265756131563314, "87": 0.34062644782381424, "88": 1.199472471555791, "89": 0.888596453502212, "90": 0.5010267035417167, "91": 0.47212306228827994, "92": 0.4468449925576742, "93": 0.6366156798312929, "94": 0.3713984117574953, "95": 0.2937468258629179, "96": 0.17792984297264905, "97": 0.4783699273439439, "98": 0.8669382043823645, "99": 0.9114832569186978, "100": 1.9076823049819824, "101": 0.6941043585819714, "102": 0.3895126556819855, "103": 0.5979833144494916, "104": 0.3318535347482629, "105": 0.22101834707390275, "106": 0.2189432578969601, "107": 0.4580114950511494, "108": 0.5384183874967178, "109": 0.7134591948000267, "110": 0.36294335934694316, "111": 0.16464903321976979, "112": 0.9746171249210827, "113": 1.1655581355712845, "114": 0.2910980443255434, "115": 1.208934164290828, "116": 0.29490324225394343, "117": 0.45506838132011784, "118": 1.0437997387982507, "119": 0.501615661550606, "120": 0.8216315250829032, "121": 0.6493954228070705, "122": 0.5216153372201294, "123": 0.8062423567823055, "124": 0.4341160285293319, "125": 0.32277637754030236, "126": 0.22024195072907327, "127": 0.304302256332134, "128": 0.31009308236498073, "129": 0.3793166903672746, "130": 1.1149490429189155, "131": 0.3636542931772222, "132": 0.6374380147880082, "133": 0.1835644029455686, "134": 0.4014830299632194, "135": 0.23080740290151489, "136": 0.945506900548935, "137": 0.0, "138": 0.0, "139": 0.0, "140": 0.0, "141": 0.0, "142": 0.0, "143": 0.0, "144": 0.0, "145": 0.0, "146": 0.0, "147": 0.0, "148": 0.0, "149": 0.0}}}, "x_name": "Index binned", "plot_shape": {"y0": -1.0009186972459163, "y1": 1.0009187004086748}}}, "bedrooms": {"type": "evidently:metric_result:ColumnDataDriftMetrics", "column_name": "bedrooms", "column_type": "num", "stattest_name": "K-S p_value", "stattest_threshold": 0.05, "drift_score": 0.08435116369069741, "drift_detected": false, "current": {"type": "evidently:metric_result:DriftStatsField", "distribution": {"type": "evidently:metric_result:Distribution", "x": [-2.665003776550293, -2.1806676728384837, -1.696331569126674, -1.2119954654148648, -0.7276593617030553, -0.24332325799124588, 0.24101284572056336, 0.725348949432373, 1.2096850531441823, 1.6940211568559915, 2.178357260567801, 2.662693364279611, 3.1470294679914197, 3.6313655717032294, 4.115701675415039], "y": [2, 0, 136, 0, 0, 300, 0, 55, 95, 0, 0, 10, 0, 2]}, "characteristic_examples": null, "characteristic_words": null, "small_distribution": {"type": "evidently:metric_result:DistributionIncluded", "x": [-2.665003776550293, -1.9869332313537598, -1.3088626861572266, -0.6307921409606934, 0.047278404235839844, 0.725348949432373, 1.4034194946289062, 2.0814900398254395, 2.7595605850219727, 3.437631130218506, 4.115701675415039], "y": [0.00491590935035704, 0.0, 0.33428183582427873, 0.737386402553556, 0.0, 0.368693201276778, 0.0, 0.024579546751785197, 0.0, 0.00491590935035704]}, "correlations": {"area": 0.2408715105561196, "bedrooms": 1.0, "house_id": -0.16264751606529304, "mainroad": 0.24981455041509879}}, "reference": {"type": "evidently:metric_result:DriftStatsField", "distribution": {"type": "evidently:metric_result:Distribution", "x": [-2.665003776550293, -2.1806676728384837, -1.696331569126674, -1.2119954654148648, -0.7276593617030553, -0.24332325799124588, 0.24101284572056336, 0.725348949432373, 1.2096850531441823, 1.6940211568559915, 2.178357260567801, 2.662693364279611, 3.1470294679914197, 3.6313655717032294, 4.115701675415039], "y": [2, 0, 136, 0, 0, 300, 0, 0, 95, 0, 0, 10, 0, 2]}, "characteristic_examples": null, "characteristic_words": null, "small_distribution": {"type": "evidently:metric_result:DistributionIncluded", "x": [-2.665003776550293, -1.9869332313537598, -1.3088626861572266, -0.6307921409606934, 0.047278404235839844, 0.725348949432373, 1.4034194946289062, 2.0814900398254395, 2.7595605850219727, 3.437631130218506, 4.115701675415039], "y": [0.0054120102939710524, 0.0, 0.3680166999900316, 0.811801544095658, 0.0, 0.25707048896362505, 0.0, 0.027060051469855264, 0.0, 0.0054120102939710524]}, "correlations": {"area": 0.15185848440562338, "bedrooms": 1.0, "house_id": -0.371096405203693, "mainroad": -0.012033243963912369}}, "scatter": {"type": "evidently:metric_result:ScatterAggField", "scatter": {"current (mean)": {"per": {"0": 0, "1": 1, "2": 2, "3": 3, "4": 4, "5": 5, "6": 6, "7": 7, "8": 8, "9": 9, "10": 10, "11": 11, "12": 12, "13": 13, "14": 14, "15": 15, "16": 16, "17": 17, "18": 18, "19": 19, "20": 20, "21": 21, "22": 22, "23": 23, "24": 24, "25": 25, "26": 26, "27": 27, "28": 28, "29": 29, "30": 30, "31": 31, "32": 32, "33": 33, "34": 34, "35": 35, "36": 36, "37": 37, "38": 38, "39": 39, "40": 40, "41": 41, "42": 42, "43": 43, "44": 44, "45": 45, "46": 46, "47": 47, "48": 48, "49": 49, "50": 50, "51": 51, "52": 52, "53": 53, "54": 54, "55": 55, "56": 56, "57": 57, "58": 58, "59": 59, "60": 60, "61": 61, "62": 62, "63": 63, "64": 64, "65": 65, "66": 66, "67": 67, "68": 68, "69": 69, "70": 70, "71": 71, "72": 72, "73": 73, "74": 74, "75": 75, "76": 76, "77": 77, "78": 78, "79": 79, "80": 80, "81": 81, "82": 82, "83": 83, "84": 84, "85": 85, "86": 86, "87": 87, "88": 88, "89": 89, "90": 90, "91": 91, "92": 92, "93": 93, "94": 94, "95": 95, "96": 96, "97": 97, "98": 98, "99": 99, "100": 100, "101": 101, "102": 102, "103": 103, "104": 104, "105": 105, "106": 106, "107": 107, "108": 108, "109": 109, "110": 110, "111": 111, "112": 112, "113": 113, "114": 114, "115": 115, "116": 116, "117": 117, "118": 118, "119": 119, "120": 120, "121": 121, "122": 122, "123": 123, "124": 124, "125": 125, "126": 126, "127": 127, "128": 128, "129": 129, "130": 130, "131": 131, "132": 132, "133": 133, "134": 134, "135": 135, "136": 136, "137": 137, "138": 138, "139": 139, "140": 140, "141": 141, "142": 142, "143": 143, "144": 144, "145": 145, "146": 146, "147": 147, "148": 148, "149": 149}, "mean": {"0": 1.0643841093406081, "1": 1.4034193521365523, "2": 0.7253488432615995, "3": 1.0643841093406081, "4": 0.38631357718259096, "5": 0.04727831110358238, "6": 0.38631357718259096, "7": 1.0643840860575438, "8": 1.0643840860575438, "9": 0.7253488432615995, "10": 0.38631357718259096, "11": 0.38631357718259096, "12": 0.04727831110358238, "13": 0.38631357718259096, "14": 1.0643841093406081, "15": 0.3863135939463973, "16": -0.29175693821161985, "17": 0.7253488432615995, "18": 0.047278327867388725, "19": 0.04727831110358238, "20": 0.04727831110358238, "21": 0.04727831110358238, "22": 0.38631357066333294, "23": 0.38631357718259096, "24": 0.38631357718259096, "25": 0.04727831110358238, "26": 0.38631357718259096, "27": 0.7253488432615995, "28": 0.7253489028662443, "29": 0.38631357718259096, "30": 0.7253488432615995, "31": 0.04727831110358238, "32": 0.38631357718259096, "33": 0.04727831110358238, "34": 0.7253488432615995, "35": 1.4034193521365523, "36": 0.047278327867388725, "37": 0.7253488432615995, "38": 0.7253488199785352, "39": 0.38631357718259096, "40": 0.7253488432615995, "41": -0.29175693821161985, "42": 0.7253488432615995, "43": 0.7253488432615995, "44": 0.04727831110358238, "45": 0.38631357718259096, "46": -0.29175693821161985, "47": -0.2917569214478135, "48": 0.047278327867388725, "49": 0.04727831110358238, "50": 0.047278327867388725, "51": -0.29175693821161985, "52": 0.04727831110358238, "53": 0.3863135939463973, "54": -0.29175693821161985, "55": 0.3863135939463973, "56": -0.9698274368420243, "57": 0.047278327867388725, "58": 0.04727831110358238, "59": 0.047278327867388725, "60": 0.04727831110358238, "61": 0.38631357718259096, "62": 0.047278327867388725, "63": -0.2917569214478135, "64": -0.29175693821161985, "65": -0.29175693821161985, "66": -0.29175693821161985, "67": 1.0643840860575438, "68": 0.3863135939463973, "69": -0.9698274368420243, "70": -0.2917569214478135, "71": -0.29175693821161985, "72": 0.047278327867388725, "73": 0.3863135939463973, "74": 0.04727831110358238, "75": 0.04727831110358238, "76": 0.04727831110358238, "77": 0.047278327867388725, "78": -0.6307921875268221, "79": 0.7253488432615995, "80": 0.04727831110358238, "81": 0.7253488432615995, "82": -0.29175693821161985, "83": -0.2917569214478135, "84": 0.3863135939463973, "85": 0.0472783213481307, "86": -0.6307921875268221, "87": -0.9698274368420243, "88": -0.6307921875268221, "89": 0.7253488367423415, "90": -0.9698274368420243, "91": -0.9698274368420243, "92": -0.9698274368420243, "93": -0.6307921875268221, "94": 0.04727831110358238, "95": -0.2917569214478135, "96": -0.6307921875268221, "97": 0.38631357718259096, "98": 1.0643841521814466, "99": -0.9698274368420243, "100": -0.6307921875268221, "101": -0.29175693821161985, "102": -0.6307921875268221, "103": -0.29175693821161985, "104": 0.3863135939463973, "105": -0.9698274368420243, "106": -0.29175693821161985, "107": 0.04727834463119507, "108": 0.3863135939463973, "109": -0.6307921875268221, "110": 0.047278327867388725, "111": -1.308862709440291, "112": -0.6307921875268221, "113": -0.29175693821161985, "114": -0.29175693821161985, "115": -0.9698274368420243, "116": -0.6307921875268221, "117": -0.6307921875268221, "118": 0.04727834463119507, "119": 0.047278327867388725, "120": -0.29175693821161985, "121": -0.6307921707630157, "122": 0.047278327867388725, "123": -0.29175693821161985, "124": -0.9698274368420243, "125": -0.29175693821161985, "126": -0.9698274368420243, "127": -0.6307921875268221, "128": -0.29175693821161985, "129": -1.3088626861572266, "130": -0.2917569214478135, "131": -1.3088626861572266, "132": -0.6307922108098865, "133": -0.2917569214478135, "134": 0.0472783213481307, "135": -0.6307921875268221, "136": 0.7618195777758956, "137": 1.0, "138": 1.0, "139": 1.0, "140": 1.0, "141": 1.0, "142": 1.0, "143": 1.0, "144": 1.0, "145": 1.0, "146": 1.0, "147": 1.0, "148": 1.0, "149": 1.0}, "std": {"0": 0.6780705321580172, "1": 1.1072845042486448, "2": 0.782968408541968, "3": 0.6780705321580172, "4": 0.6780705321580172, "5": 0.0, "6": 0.6780705321580172, "7": 1.2984061763870904, "8": 1.2984061763870904, "9": 0.782968408541968, "10": 0.6780705321580172, "11": 0.6780705321580172, "12": 0.0, "13": 0.6780705321580172, "14": 0.6780705321580172, "15": 1.2984061877356619, "16": 0.6780704986304045, "17": 0.782968408541968, "18": 1.1072845148945485, "19": 0.0, "20": 0.0, "21": 0.0, "22": 1.7064400190306086, "23": 0.6780705321580172, "24": 0.6780705321580172, "25": 0.0, "26": 0.6780705321580172, "27": 0.782968408541968, "28": 2.3489052887159603, "29": 0.6780705321580172, "30": 0.782968408541968, "31": 0.0, "32": 0.6780705321580172, "33": 0.0, "34": 0.782968408541968, "35": 1.1072845042486448, "36": 1.1072845148945485, "37": 0.782968408541968, "38": 1.3561410177499056, "39": 0.6780705321580172, "40": 0.782968408541968, "41": 0.6780704986304045, "42": 0.782968408541968, "43": 0.782968408541968, "44": 0.0, "45": 0.6780705321580172, "46": 0.6780704986304045, "47": 1.2984061818992536, "48": 1.1072845148945485, "49": 0.0, "50": 1.1072845148945485, "51": 0.6780704986304045, "52": 0.0, "53": 1.2984061877356619, "54": 0.6780704986304045, "55": 1.2984061877356619, "56": 0.6780704986304045, "57": 1.1072845148945485, "58": 0.0, "59": 1.1072845148945485, "60": 0.0, "61": 0.6780705321580172, "62": 1.1072845148945485, "63": 1.2984061818992536, "64": 0.6780704986304045, "65": 0.6780704986304045, "66": 0.6780704986304045, "67": 1.2984061763870904, "68": 1.2984061877356616, "69": 0.6780704986304045, "70": 1.2984061818992538, "71": 0.6780704986304045, "72": 1.1072845148945485, "73": 1.2984061877356619, "74": 0.0, "75": 0.0, "76": 0.0, "77": 1.1072845148945485, "78": 0.7829683698276155, "79": 0.782968408541968, "80": 0.0, "81": 0.782968408541968, "82": 0.6780704986304045, "83": 1.2984061818992536, "84": 1.2984061877356619, "85": 1.917873010133716, "86": 0.7829683698276155, "87": 0.6780704986304045, "88": 0.7829683698276155, "89": 1.750770523694322, "90": 0.6780704986304045, "91": 0.6780704986304045, "92": 0.6780704986304045, "93": 0.7829683698276155, "94": 0.0, "95": 1.2984061818992538, "96": 0.7829683698276155, "97": 0.6780705321580172, "98": 2.0342116821557283, "99": 0.6780704986304045, "100": 0.7829683698276155, "101": 0.6780704986304045, "102": 0.7829683698276155, "103": 0.6780704986304045, "104": 1.2984061877356619, "105": 0.6780704986304045, "106": 0.6780704986304045, "107": 1.5659367783695837, "108": 1.2984061877356616, "109": 0.7829683698276155, "110": 1.1072845148945485, "111": 1.1072845255404524, "112": 0.7829683698276155, "113": 0.6780704986304045, "114": 0.6780704986304045, "115": 0.6780704986304045, "116": 0.7829683698276155, "117": 0.7829683698276155, "118": 1.5659367783695837, "119": 1.1072845148945485, "120": 0.6780704986304045, "121": 1.3561410307884216, "122": 1.1072845148945485, "123": 0.6780704986304045, "124": 0.6780704986304045, "125": 0.6780704986304045, "126": 0.6780704986304045, "127": 0.7829683698276155, "128": 0.6780704986304045, "129": 0.0, "130": 1.2984061818992538, "131": 0.0, "132": 1.3561410438269377, "133": 1.2984061818992536, "134": 1.917873010133716, "135": 0.7829683698276155, "136": 0.47636084444820875, "137": 0.0, "138": 0.0, "139": 0.0, "140": 0.0, "141": 0.0, "142": 0.0, "143": 0.0, "144": 0.0, "145": 0.0, "146": 0.0, "147": 0.0, "148": 0.0, "149": 0.0}}}, "x_name": "Index binned", "plot_shape": {"y0": -1.0009186703796578, "y1": 1.0009186995257824}}}, "house_id": {"type": "evidently:metric_result:ColumnDataDriftMetrics", "column_name": "house_id", "column_type": "num", "stattest_name": "K-S p_value", "stattest_threshold": 0.05, "drift_score": 0.015133698982184583, "drift_detected": true, "current": {"type": "evidently:metric_result:DriftStatsField", "distribution": {"type": "evidently:metric_result:Distribution", "x": [1.0, 50.916666666666664, 100.83333333333333, 150.75, 200.66666666666666, 250.58333333333331, 300.5, 350.41666666666663, 400.3333333333333, 450.25, 500.16666666666663, 550.0833333333333, 600.0], "y": [50, 50, 50, 50, 50, 50, 50, 50, 50, 50, 50, 50]}, "characteristic_examples": null, "characteristic_words": null, "small_distribution": {"type": "evidently:metric_result:DistributionIncluded", "x": [1.0, 60.9, 120.8, 180.7, 240.6, 300.5, 360.4, 420.3, 480.2, 540.1, 600.0], "y": [0.001669449081803005, 0.001669449081803005, 0.0016694490818030053, 0.001669449081803005, 0.001669449081803005, 0.0016694490818030057, 0.001669449081803004, 0.0016694490818030057, 0.001669449081803004, 0.0016694490818030057]}, "correlations": {"area": -0.2546058857142971, "bedrooms": -0.16264751606529304, "house_id": 0.9999999999999999, "mainroad": 0.30157427336522064}}, "reference": {"type": "evidently:metric_result:DriftStatsField", "distribution": {"type": "evidently:metric_result:Distribution", "x": [1.0, 50.916666666666664, 100.83333333333333, 150.75, 200.66666666666666, 250.58333333333331, 300.5, 350.41666666666663, 400.3333333333333, 450.25, 500.16666666666663, 550.0833333333333, 600.0], "y": [50, 50, 50, 50, 50, 50, 50, 50, 50, 50, 45, 0]}, "characteristic_examples": null, "characteristic_words": null, "small_distribution": {"type": "evidently:metric_result:DistributionIncluded", "x": [1.0, 55.4, 109.8, 164.2, 218.6, 273.0, 327.4, 381.8, 436.2, 490.59999999999997, 545.0], "y": [0.0018550998381003778, 0.0018213707501349163, 0.0018550998381003782, 0.001821370750134916, 0.001821370750134916, 0.0018550998381003784, 0.0018213707501349152, 0.0018550998381003784, 0.0018213707501349172, 0.0018550998381003765]}, "correlations": {"area": -0.5414678104835224, "bedrooms": -0.37109640520369297, "house_id": 1.0, "mainroad": -0.338514844685224}}, "scatter": {"type": "evidently:metric_result:ScatterAggField", "scatter": {"current (mean)": {"per": {"0": 0, "1": 1, "2": 2, "3": 3, "4": 4, "5": 5, "6": 6, "7": 7, "8": 8, "9": 9, "10": 10, "11": 11, "12": 12, "13": 13, "14": 14, "15": 15, "16": 16, "17": 17, "18": 18, "19": 19, "20": 20, "21": 21, "22": 22, "23": 23, "24": 24, "25": 25, "26": 26, "27": 27, "28": 28, "29": 29, "30": 30, "31": 31, "32": 32, "33": 33, "34": 34, "35": 35, "36": 36, "37": 37, "38": 38, "39": 39, "40": 40, "41": 41, "42": 42, "43": 43, "44": 44, "45": 45, "46": 46, "47": 47, "48": 48, "49": 49, "50": 50, "51": 51, "52": 52, "53": 53, "54": 54, "55": 55, "56": 56, "57": 57, "58": 58, "59": 59, "60": 60, "61": 61, "62": 62, "63": 63, "64": 64, "65": 65, "66": 66, "67": 67, "68": 68, "69": 69, "70": 70, "71": 71, "72": 72, "73": 73, "74": 74, "75": 75, "76": 76, "77": 77, "78": 78, "79": 79, "80": 80, "81": 81, "82": 82, "83": 83, "84": 84, "85": 85, "86": 86, "87": 87, "88": 88, "89": 89, "90": 90, "91": 91, "92": 92, "93": 93, "94": 94, "95": 95, "96": 96, "97": 97, "98": 98, "99": 99, "100": 100, "101": 101, "102": 102, "103": 103, "104": 104, "105": 105, "106": 106, "107": 107, "108": 108, "109": 109, "110": 110, "111": 111, "112": 112, "113": 113, "114": 114, "115": 115, "116": 116, "117": 117, "118": 118, "119": 119, "120": 120, "121": 121, "122": 122, "123": 123, "124": 124, "125": 125, "126": 126, "127": 127, "128": 128, "129": 129, "130": 130, "131": 131, "132": 132, "133": 133, "134": 134, "135": 135, "136": 136, "137": 137, "138": 138, "139": 139, "140": 140, "141": 141, "142": 142, "143": 143, "144": 144, "145": 145, "146": 146, "147": 147, "148": 148, "149": 149}, "mean": {"0": 2.5, "1": 6.5, "2": 10.5, "3": 14.5, "4": 18.5, "5": 22.5, "6": 26.5, "7": 30.5, "8": 34.5, "9": 38.5, "10": 42.5, "11": 46.5, "12": 50.5, "13": 54.5, "14": 58.5, "15": 62.5, "16": 66.5, "17": 70.5, "18": 74.5, "19": 78.5, "20": 82.5, "21": 86.5, "22": 90.5, "23": 94.5, "24": 98.5, "25": 102.5, "26": 106.5, "27": 110.5, "28": 114.5, "29": 118.5, "30": 122.5, "31": 126.5, "32": 130.5, "33": 134.5, "34": 138.5, "35": 142.5, "36": 146.5, "37": 150.5, "38": 154.5, "39": 158.5, "40": 162.5, "41": 166.5, "42": 170.5, "43": 174.5, "44": 178.5, "45": 182.5, "46": 186.5, "47": 190.5, "48": 194.5, "49": 198.5, "50": 202.5, "51": 206.5, "52": 210.5, "53": 214.5, "54": 218.5, "55": 222.5, "56": 226.5, "57": 230.5, "58": 234.5, "59": 238.5, "60": 242.5, "61": 246.5, "62": 250.5, "63": 254.5, "64": 258.5, "65": 262.5, "66": 266.5, "67": 270.5, "68": 274.5, "69": 278.5, "70": 282.5, "71": 286.5, "72": 290.5, "73": 294.5, "74": 298.5, "75": 302.5, "76": 306.5, "77": 310.5, "78": 314.5, "79": 318.5, "80": 322.5, "81": 326.5, "82": 330.5, "83": 334.5, "84": 338.5, "85": 342.5, "86": 346.5, "87": 350.5, "88": 354.5, "89": 358.5, "90": 362.5, "91": 366.5, "92": 370.5, "93": 374.5, "94": 378.5, "95": 382.5, "96": 386.5, "97": 390.5, "98": 394.5, "99": 398.5, "100": 402.5, "101": 406.5, "102": 410.5, "103": 414.5, "104": 418.5, "105": 422.5, "106": 426.5, "107": 430.5, "108": 434.5, "109": 438.5, "110": 442.5, "111": 446.5, "112": 450.5, "113": 454.5, "114": 458.5, "115": 462.5, "116": 466.5, "117": 470.5, "118": 474.5, "119": 478.5, "120": 482.5, "121": 486.5, "122": 490.5, "123": 494.5, "124": 498.5, "125": 502.5, "126": 506.5, "127": 510.5, "128": 514.5, "129": 518.5, "130": 522.5, "131": 526.5, "132": 530.5, "133": 534.5, "134": 538.5, "135": 542.5, "136": 546.5, "137": 550.5, "138": 554.5, "139": 558.5, "140": 562.5, "141": 566.5, "142": 570.5, "143": 574.5, "144": 578.5, "145": 582.5, "146": 586.5, "147": 590.5, "148": 594.5, "149": 598.5}, "std": {"0": 1.2909944487358056, "1": 1.2909944487358056, "2": 1.2909944487358056, "3": 1.2909944487358056, "4": 1.2909944487358056, "5": 1.2909944487358056, "6": 1.2909944487358056, "7": 1.2909944487358056, "8": 1.2909944487358056, "9": 1.2909944487358056, "10": 1.2909944487358056, "11": 1.2909944487358056, "12": 1.2909944487358056, "13": 1.2909944487358056, "14": 1.2909944487358056, "15": 1.2909944487358056, "16": 1.2909944487358056, "17": 1.2909944487358056, "18": 1.2909944487358056, "19": 1.2909944487358056, "20": 1.2909944487358056, "21": 1.2909944487358056, "22": 1.2909944487358056, "23": 1.2909944487358056, "24": 1.2909944487358056, "25": 1.2909944487358056, "26": 1.2909944487358056, "27": 1.2909944487358056, "28": 1.2909944487358056, "29": 1.2909944487358056, "30": 1.2909944487358056, "31": 1.2909944487358056, "32": 1.2909944487358056, "33": 1.2909944487358056, "34": 1.2909944487358056, "35": 1.2909944487358056, "36": 1.2909944487358056, "37": 1.2909944487358056, "38": 1.2909944487358056, "39": 1.2909944487358056, "40": 1.2909944487358056, "41": 1.2909944487358056, "42": 1.2909944487358056, "43": 1.2909944487358056, "44": 1.2909944487358056, "45": 1.2909944487358056, "46": 1.2909944487358056, "47": 1.2909944487358056, "48": 1.2909944487358056, "49": 1.2909944487358056, "50": 1.2909944487358056, "51": 1.2909944487358056, "52": 1.2909944487358056, "53": 1.2909944487358056, "54": 1.2909944487358056, "55": 1.2909944487358056, "56": 1.2909944487358056, "57": 1.2909944487358056, "58": 1.2909944487358056, "59": 1.2909944487358056, "60": 1.2909944487358056, "61": 1.2909944487358056, "62": 1.2909944487358056, "63": 1.2909944487358056, "64": 1.2909944487358056, "65": 1.2909944487358056, "66": 1.2909944487358056, "67": 1.2909944487358056, "68": 1.2909944487358056, "69": 1.2909944487358056, "70": 1.2909944487358056, "71": 1.2909944487358056, "72": 1.2909944487358056, "73": 1.2909944487358056, "74": 1.2909944487358056, "75": 1.2909944487358056, "76": 1.2909944487358056, "77": 1.2909944487358056, "78": 1.2909944487358056, "79": 1.2909944487358056, "80": 1.2909944487358056, "81": 1.2909944487358056, "82": 1.2909944487358056, "83": 1.2909944487358056, "84": 1.2909944487358056, "85": 1.2909944487358056, "86": 1.2909944487358056, "87": 1.2909944487358056, "88": 1.2909944487358056, "89": 1.2909944487358056, "90": 1.2909944487358056, "91": 1.2909944487358056, "92": 1.2909944487358056, "93": 1.2909944487358056, "94": 1.2909944487358056, "95": 1.2909944487358056, "96": 1.2909944487358056, "97": 1.2909944487358056, "98": 1.2909944487358056, "99": 1.2909944487358056, "100": 1.2909944487358056, "101": 1.2909944487358056, "102": 1.2909944487358056, "103": 1.2909944487358056, "104": 1.2909944487358056, "105": 1.2909944487358056, "106": 1.2909944487358056, "107": 1.2909944487358056, "108": 1.2909944487358056, "109": 1.2909944487358056, "110": 1.2909944487358056, "111": 1.2909944487358056, "112": 1.2909944487358056, "113": 1.2909944487358056, "114": 1.2909944487358056, "115": 1.2909944487358056, "116": 1.2909944487358056, "117": 1.2909944487358056, "118": 1.2909944487358056, "119": 1.2909944487358056, "120": 1.2909944487358056, "121": 1.2909944487358056, "122": 1.2909944487358056, "123": 1.2909944487358056, "124": 1.2909944487358056, "125": 1.2909944487358056, "126": 1.2909944487358056, "127": 1.2909944487358056, "128": 1.2909944487358056, "129": 1.2909944487358056, "130": 1.2909944487358056, "131": 1.2909944487358056, "132": 1.2909944487358056, "133": 1.2909944487358056, "134": 1.2909944487358056, "135": 1.2909944487358056, "136": 1.2909944487358056, "137": 1.2909944487358056, "138": 1.2909944487358056, "139": 1.2909944487358056, "140": 1.2909944487358056, "141": 1.2909944487358056, "142": 1.2909944487358056, "143": 1.2909944487358056, "144": 1.2909944487358056, "145": 1.2909944487358056, "146": 1.2909944487358056, "147": 1.2909944487358056, "148": 1.2909944487358056, "149": 1.2909944487358056}}}, "x_name": "Index binned", "plot_shape": {"y0": 115.52778022774939, "y1": 430.4722197722506}}}, "mainroad": {"type": "evidently:metric_result:ColumnDataDriftMetrics", "column_name": "mainroad", "column_type": "num", "stattest_name": "chi-square p_value", "stattest_threshold": 0.05, "drift_score": 0.0, "drift_detected": true, "current": {"type": "evidently:metric_result:DriftStatsField", "distribution": {"type": "evidently:metric_result:Distribution", "x": [0.0, 0.1875, 0.375, 0.5625, 0.75, 0.9375, 1.125, 1.3125, 1.5, 1.6875, 1.875, 2.0625, 2.25, 2.4375, 2.625, 2.8125, 3.0], "y": [77, 0, 0, 0, 0, 468, 0, 0, 0, 0, 0, 0, 0, 0, 0, 55]}, "characteristic_examples": null, "characteristic_words": null, "small_distribution": {"type": "evidently:metric_result:DistributionIncluded", "x": [0.0, 0.3, 0.6, 0.8999999999999999, 1.2, 1.5, 1.7999999999999998, 2.1, 2.4, 2.6999999999999997, 3.0], "y": [0.4277777777777778, 0.0, 0.0, 2.5999999999999996, 0.0, 0.0, 0.0, 0.0, 0.0, 0.3055555555555553]}, "correlations": {"area": 0.44806688917874476, "bedrooms": 0.24981455041509879, "house_id": 0.30157427336522064, "mainroad": 0.9999999999999999}}, "reference": {"type": "evidently:metric_result:DriftStatsField", "distribution": {"type": "evidently:metric_result:Distribution", "x": [0.0, 0.1875, 0.375, 0.5625, 0.75, 0.9375, 1.125, 1.3125, 1.5, 1.6875, 1.875, 2.0625, 2.25, 2.4375, 2.625, 2.8125, 3.0], "y": [77, 0, 0, 0, 0, 468, 0, 0, 0, 0, 0, 0, 0, 0, 0, 0]}, "characteristic_examples": null, "characteristic_words": null, "small_distribution": {"type": "evidently:metric_result:DistributionIncluded", "x": [0.0, 0.1, 0.2, 0.30000000000000004, 0.4, 0.5, 0.6000000000000001, 0.7000000000000001, 0.8, 0.9, 1.0], "y": [1.4128440366972477, 0.0, 0.0, 0.0, 0.0, 0.0, 0.0, 0.0, 0.0, 8.587155963302754]}, "correlations": {"area": 0.2888741122781703, "bedrooms": -0.012033243963912369, "house_id": -0.338514844685224, "mainroad": 1.0}}, "scatter": {"type": "evidently:metric_result:ScatterAggField", "scatter": {"current (mean)": {"per": {"0": 0, "1": 1, "2": 2, "3": 3, "4": 4, "5": 5, "6": 6, "7": 7, "8": 8, "9": 9, "10": 10, "11": 11, "12": 12, "13": 13, "14": 14, "15": 15, "16": 16, "17": 17, "18": 18, "19": 19, "20": 20, "21": 21, "22": 22, "23": 23, "24": 24, "25": 25, "26": 26, "27": 27, "28": 28, "29": 29, "30": 30, "31": 31, "32": 32, "33": 33, "34": 34, "35": 35, "36": 36, "37": 37, "38": 38, "39": 39, "40": 40, "41": 41, "42": 42, "43": 43, "44": 44, "45": 45, "46": 46, "47": 47, "48": 48, "49": 49, "50": 50, "51": 51, "52": 52, "53": 53, "54": 54, "55": 55, "56": 56, "57": 57, "58": 58, "59": 59, "60": 60, "61": 61, "62": 62, "63": 63, "64": 64, "65": 65, "66": 66, "67": 67, "68": 68, "69": 69, "70": 70, "71": 71, "72": 72, "73": 73, "74": 74, "75": 75, "76": 76, "77": 77, "78": 78, "79": 79, "80": 80, "81": 81, "82": 82, "83": 83, "84": 84, "85": 85, "86": 86, "87": 87, "88": 88, "89": 89, "90": 90, "91": 91, "92": 92, "93": 93, "94": 94, "95": 95, "96": 96, "97": 97, "98": 98, "99": 99, "100": 100, "101": 101, "102": 102, "103": 103, "104": 104, "105": 105, "106": 106, "107": 107, "108": 108, "109": 109, "110": 110, "111": 111, "112": 112, "113": 113, "114": 114, "115": 115, "116": 116, "117": 117, "118": 118, "119": 119, "120": 120, "121": 121, "122": 122, "123": 123, "124": 124, "125": 125, "126": 126, "127": 127, "128": 128, "129": 129, "130": 130, "131": 131, "132": 132, "133": 133, "134": 134, "135": 135, "136": 136, "137": 137, "138": 138, "139": 139, "140": 140, "141": 141, "142": 142, "143": 143, "144": 144, "145": 145, "146": 146, "147": 147, "148": 148, "149": 149}, "mean": {"0": 1.0, "1": 1.0, "2": 1.0, "3": 1.0, "4": 1.0, "5": 1.0, "6": 1.0, "7": 1.0, "8": 1.0, "9": 1.0, "10": 1.0, "11": 1.0, "12": 1.0, "13": 1.0, "14": 1.0, "15": 1.0, "16": 1.0, "17": 1.0, "18": 1.0, "19": 1.0, "20": 1.0, "21": 1.0, "22": 1.0, "23": 1.0, "24": 1.0, "25": 1.0, "26": 1.0, "27": 1.0, "28": 1.0, "29": 1.0, "30": 1.0, "31": 1.0, "32": 1.0, "33": 1.0, "34": 1.0, "35": 0.75, "36": 1.0, "37": 1.0, "38": 1.0, "39": 0.75, "40": 1.0, "41": 1.0, "42": 0.75, "43": 1.0, "44": 1.0, "45": 0.5, "46": 1.0, "47": 0.75, "48": 1.0, "49": 0.75, "50": 0.75, "51": 1.0, "52": 1.0, "53": 1.0, "54": 1.0, "55": 1.0, "56": 1.0, "57": 1.0, "58": 1.0, "59": 1.0, "60": 1.0, "61": 1.0, "62": 1.0, "63": 1.0, "64": 1.0, "65": 0.75, "66": 1.0, "67": 0.75, "68": 1.0, "69": 1.0, "70": 0.75, "71": 1.0, "72": 0.75, "73": 0.0, "74": 1.0, "75": 1.0, "76": 1.0, "77": 1.0, "78": 1.0, "79": 0.75, "80": 1.0, "81": 0.25, "82": 0.75, "83": 1.0, "84": 1.0, "85": 1.0, "86": 1.0, "87": 0.75, "88": 1.0, "89": 0.5, "90": 1.0, "91": 0.75, "92": 0.75, "93": 0.75, "94": 0.75, "95": 1.0, "96": 0.75, "97": 0.75, "98": 0.5, "99": 1.0, "100": 1.0, "101": 0.75, "102": 1.0, "103": 1.0, "104": 0.75, "105": 0.75, "106": 0.5, "107": 0.75, "108": 0.75, "109": 0.5, "110": 0.75, "111": 0.25, "112": 0.75, "113": 1.0, "114": 0.75, "115": 0.75, "116": 0.75, "117": 0.75, "118": 0.75, "119": 0.5, "120": 0.25, "121": 0.75, "122": 0.25, "123": 1.0, "124": 0.75, "125": 0.75, "126": 0.75, "127": 0.5, "128": 0.75, "129": 0.75, "130": 0.75, "131": 0.75, "132": 0.25, "133": 0.75, "134": 0.5, "135": 0.5, "136": 2.5, "137": 3.0, "138": 3.0, "139": 3.0, "140": 3.0, "141": 3.0, "142": 3.0, "143": 3.0, "144": 3.0, "145": 3.0, "146": 3.0, "147": 3.0, "148": 3.0, "149": 3.0}, "std": {"0": 0.0, "1": 0.0, "2": 0.0, "3": 0.0, "4": 0.0, "5": 0.0, "6": 0.0, "7": 0.0, "8": 0.0, "9": 0.0, "10": 0.0, "11": 0.0, "12": 0.0, "13": 0.0, "14": 0.0, "15": 0.0, "16": 0.0, "17": 0.0, "18": 0.0, "19": 0.0, "20": 0.0, "21": 0.0, "22": 0.0, "23": 0.0, "24": 0.0, "25": 0.0, "26": 0.0, "27": 0.0, "28": 0.0, "29": 0.0, "30": 0.0, "31": 0.0, "32": 0.0, "33": 0.0, "34": 0.0, "35": 0.5, "36": 0.0, "37": 0.0, "38": 0.0, "39": 0.5, "40": 0.0, "41": 0.0, "42": 0.5, "43": 0.0, "44": 0.0, "45": 0.5773502691896257, "46": 0.0, "47": 0.5, "48": 0.0, "49": 0.5, "50": 0.5, "51": 0.0, "52": 0.0, "53": 0.0, "54": 0.0, "55": 0.0, "56": 0.0, "57": 0.0, "58": 0.0, "59": 0.0, "60": 0.0, "61": 0.0, "62": 0.0, "63": 0.0, "64": 0.0, "65": 0.5, "66": 0.0, "67": 0.5, "68": 0.0, "69": 0.0, "70": 0.5, "71": 0.0, "72": 0.5, "73": 0.0, "74": 0.0, "75": 0.0, "76": 0.0, "77": 0.0, "78": 0.0, "79": 0.5, "80": 0.0, "81": 0.5, "82": 0.5, "83": 0.0, "84": 0.0, "85": 0.0, "86": 0.0, "87": 0.5, "88": 0.0, "89": 0.5773502691896257, "90": 0.0, "91": 0.5, "92": 0.5, "93": 0.5, "94": 0.5, "95": 0.0, "96": 0.5, "97": 0.5, "98": 0.5773502691896257, "99": 0.0, "100": 0.0, "101": 0.5, "102": 0.0, "103": 0.0, "104": 0.5, "105": 0.5, "106": 0.5773502691896257, "107": 0.5, "108": 0.5, "109": 0.5773502691896257, "110": 0.5, "111": 0.5, "112": 0.5, "113": 0.0, "114": 0.5, "115": 0.5, "116": 0.5, "117": 0.5, "118": 0.5, "119": 0.5773502691896257, "120": 0.5, "121": 0.5, "122": 0.5, "123": 0.0, "124": 0.5, "125": 0.5, "126": 0.5, "127": 0.5773502691896257, "128": 0.5, "129": 0.5, "130": 0.5, "131": 0.5, "132": 0.5, "133": 0.5, "134": 0.5773502691896257, "135": 0.5773502691896257, "136": 1.0, "137": 0.0, "138": 0.0, "139": 0.0, "140": 0.0, "141": 0.0, "142": 0.0, "143": 0.0, "144": 0.0, "145": 0.0, "146": 0.0, "147": 0.0, "148": 0.0, "149": 0.0}}}, "x_name": "Index binned", "plot_shape": {"y0": 0.510080914474989, "y1": 1.2073502781855616}}}}, "dataset_columns": {"type": "evidently:metric_result:DatasetColumns", "utility_columns": {"type": "evidently:metric_result:DatasetUtilityColumns", "date": null, "id": null, "target": null, "prediction": null}, "target_type": null, "num_feature_names": ["area", "bedrooms", "house_id", "mainroad"], "cat_feature_names": [], "text_feature_names": [], "datetime_feature_names": [], "target_names": null, "task": null}, "current_fi": null, "reference_fi": null}, {"type": "evidently:metric_result:ColumnDataDriftMetrics", "column_name": "mainroad", "column_type": "cat", "stattest_name": "chi-square p_value", "stattest_threshold": 0.05, "drift_score": 0.0, "drift_detected": true, "current": {"type": "evidently:metric_result:DriftStatsField", "distribution": {"type": "evidently:metric_result:Distribution", "x": [1, 0, 3], "y": [468, 77, 55]}, "characteristic_examples": null, "characteristic_words": null, "small_distribution": {"type": "evidently:metric_result:DistributionIncluded", "x": [0, 1, 3], "y": [77, 468, 55]}, "correlations": null}, "reference": {"type": "evidently:metric_result:DriftStatsField", "distribution": {"type": "evidently:metric_result:Distribution", "x": [1, 0], "y": [468, 77]}, "characteristic_examples": null, "characteristic_words": null, "small_distribution": {"type": "evidently:metric_result:DistributionIncluded", "x": [0, 1, 3], "y": [77, 468, 0]}, "correlations": null}, "scatter": null}, {"type": "evidently:metric_result:ColumnDataDriftMetrics", "column_name": "house_id", "column_type": "num", "stattest_name": "K-S p_value", "stattest_threshold": 0.05, "drift_score": 0.015133698982184583, "drift_detected": true, "current": {"type": "evidently:metric_result:DriftStatsField", "distribution": {"type": "evidently:metric_result:Distribution", "x": [1.0, 50.916666666666664, 100.83333333333333, 150.75, 200.66666666666666, 250.58333333333331, 300.5, 350.41666666666663, 400.3333333333333, 450.25, 500.16666666666663, 550.0833333333333, 600.0], "y": [50, 50, 50, 50, 50, 50, 50, 50, 50, 50, 50, 50]}, "characteristic_examples": null, "characteristic_words": null, "small_distribution": {"type": "evidently:metric_result:DistributionIncluded", "x": [1.0, 60.9, 120.8, 180.7, 240.6, 300.5, 360.4, 420.3, 480.2, 540.1, 600.0], "y": [0.001669449081803005, 0.001669449081803005, 0.0016694490818030053, 0.001669449081803005, 0.001669449081803005, 0.0016694490818030057, 0.001669449081803004, 0.0016694490818030057, 0.001669449081803004, 0.0016694490818030057]}, "correlations": null}, "reference": {"type": "evidently:metric_result:DriftStatsField", "distribution": {"type": "evidently:metric_result:Distribution", "x": [1.0, 50.916666666666664, 100.83333333333333, 150.75, 200.66666666666666, 250.58333333333331, 300.5, 350.41666666666663, 400.3333333333333, 450.25, 500.16666666666663, 550.0833333333333, 600.0], "y": [50, 50, 50, 50, 50, 50, 50, 50, 50, 50, 45, 0]}, "characteristic_examples": null, "characteristic_words": null, "small_distribution": {"type": "evidently:metric_result:DistributionIncluded", "x": [1.0, 55.4, 109.8, 164.2, 218.6, 273.0, 327.4, 381.8, 436.2, 490.59999999999997, 545.0], "y": [0.0018550998381003778, 0.0018213707501349163, 0.0018550998381003782, 0.001821370750134916, 0.001821370750134916, 0.0018550998381003784, 0.0018213707501349152, 0.0018550998381003784, 0.0018213707501349172, 0.0018550998381003765]}, "correlations": null}, "scatter": {"type": "evidently:metric_result:ScatterAggField", "scatter": {"current (mean)": {"per": {"0": 0, "1": 1, "2": 2, "3": 3, "4": 4, "5": 5, "6": 6, "7": 7, "8": 8, "9": 9, "10": 10, "11": 11, "12": 12, "13": 13, "14": 14, "15": 15, "16": 16, "17": 17, "18": 18, "19": 19, "20": 20, "21": 21, "22": 22, "23": 23, "24": 24, "25": 25, "26": 26, "27": 27, "28": 28, "29": 29, "30": 30, "31": 31, "32": 32, "33": 33, "34": 34, "35": 35, "36": 36, "37": 37, "38": 38, "39": 39, "40": 40, "41": 41, "42": 42, "43": 43, "44": 44, "45": 45, "46": 46, "47": 47, "48": 48, "49": 49, "50": 50, "51": 51, "52": 52, "53": 53, "54": 54, "55": 55, "56": 56, "57": 57, "58": 58, "59": 59, "60": 60, "61": 61, "62": 62, "63": 63, "64": 64, "65": 65, "66": 66, "67": 67, "68": 68, "69": 69, "70": 70, "71": 71, "72": 72, "73": 73, "74": 74, "75": 75, "76": 76, "77": 77, "78": 78, "79": 79, "80": 80, "81": 81, "82": 82, "83": 83, "84": 84, "85": 85, "86": 86, "87": 87, "88": 88, "89": 89, "90": 90, "91": 91, "92": 92, "93": 93, "94": 94, "95": 95, "96": 96, "97": 97, "98": 98, "99": 99, "100": 100, "101": 101, "102": 102, "103": 103, "104": 104, "105": 105, "106": 106, "107": 107, "108": 108, "109": 109, "110": 110, "111": 111, "112": 112, "113": 113, "114": 114, "115": 115, "116": 116, "117": 117, "118": 118, "119": 119, "120": 120, "121": 121, "122": 122, "123": 123, "124": 124, "125": 125, "126": 126, "127": 127, "128": 128, "129": 129, "130": 130, "131": 131, "132": 132, "133": 133, "134": 134, "135": 135, "136": 136, "137": 137, "138": 138, "139": 139, "140": 140, "141": 141, "142": 142, "143": 143, "144": 144, "145": 145, "146": 146, "147": 147, "148": 148, "149": 149}, "mean": {"0": 2.5, "1": 6.5, "2": 10.5, "3": 14.5, "4": 18.5, "5": 22.5, "6": 26.5, "7": 30.5, "8": 34.5, "9": 38.5, "10": 42.5, "11": 46.5, "12": 50.5, "13": 54.5, "14": 58.5, "15": 62.5, "16": 66.5, "17": 70.5, "18": 74.5, "19": 78.5, "20": 82.5, "21": 86.5, "22": 90.5, "23": 94.5, "24": 98.5, "25": 102.5, "26": 106.5, "27": 110.5, "28": 114.5, "29": 118.5, "30": 122.5, "31": 126.5, "32": 130.5, "33": 134.5, "34": 138.5, "35": 142.5, "36": 146.5, "37": 150.5, "38": 154.5, "39": 158.5, "40": 162.5, "41": 166.5, "42": 170.5, "43": 174.5, "44": 178.5, "45": 182.5, "46": 186.5, "47": 190.5, "48": 194.5, "49": 198.5, "50": 202.5, "51": 206.5, "52": 210.5, "53": 214.5, "54": 218.5, "55": 222.5, "56": 226.5, "57": 230.5, "58": 234.5, "59": 238.5, "60": 242.5, "61": 246.5, "62": 250.5, "63": 254.5, "64": 258.5, "65": 262.5, "66": 266.5, "67": 270.5, "68": 274.5, "69": 278.5, "70": 282.5, "71": 286.5, "72": 290.5, "73": 294.5, "74": 298.5, "75": 302.5, "76": 306.5, "77": 310.5, "78": 314.5, "79": 318.5, "80": 322.5, "81": 326.5, "82": 330.5, "83": 334.5, "84": 338.5, "85": 342.5, "86": 346.5, "87": 350.5, "88": 354.5, "89": 358.5, "90": 362.5, "91": 366.5, "92": 370.5, "93": 374.5, "94": 378.5, "95": 382.5, "96": 386.5, "97": 390.5, "98": 394.5, "99": 398.5, "100": 402.5, "101": 406.5, "102": 410.5, "103": 414.5, "104": 418.5, "105": 422.5, "106": 426.5, "107": 430.5, "108": 434.5, "109": 438.5, "110": 442.5, "111": 446.5, "112": 450.5, "113": 454.5, "114": 458.5, "115": 462.5, "116": 466.5, "117": 470.5, "118": 474.5, "119": 478.5, "120": 482.5, "121": 486.5, "122": 490.5, "123": 494.5, "124": 498.5, "125": 502.5, "126": 506.5, "127": 510.5, "128": 514.5, "129": 518.5, "130": 522.5, "131": 526.5, "132": 530.5, "133": 534.5, "134": 538.5, "135": 542.5, "136": 546.5, "137": 550.5, "138": 554.5, "139": 558.5, "140": 562.5, "141": 566.5, "142": 570.5, "143": 574.5, "144": 578.5, "145": 582.5, "146": 586.5, "147": 590.5, "148": 594.5, "149": 598.5}, "std": {"0": 1.2909944487358056, "1": 1.2909944487358056, "2": 1.2909944487358056, "3": 1.2909944487358056, "4": 1.2909944487358056, "5": 1.2909944487358056, "6": 1.2909944487358056, "7": 1.2909944487358056, "8": 1.2909944487358056, "9": 1.2909944487358056, "10": 1.2909944487358056, "11": 1.2909944487358056, "12": 1.2909944487358056, "13": 1.2909944487358056, "14": 1.2909944487358056, "15": 1.2909944487358056, "16": 1.2909944487358056, "17": 1.2909944487358056, "18": 1.2909944487358056, "19": 1.2909944487358056, "20": 1.2909944487358056, "21": 1.2909944487358056, "22": 1.2909944487358056, "23": 1.2909944487358056, "24": 1.2909944487358056, "25": 1.2909944487358056, "26": 1.2909944487358056, "27": 1.2909944487358056, "28": 1.2909944487358056, "29": 1.2909944487358056, "30": 1.2909944487358056, "31": 1.2909944487358056, "32": 1.2909944487358056, "33": 1.2909944487358056, "34": 1.2909944487358056, "35": 1.2909944487358056, "36": 1.2909944487358056, "37": 1.2909944487358056, "38": 1.2909944487358056, "39": 1.2909944487358056, "40": 1.2909944487358056, "41": 1.2909944487358056, "42": 1.2909944487358056, "43": 1.2909944487358056, "44": 1.2909944487358056, "45": 1.2909944487358056, "46": 1.2909944487358056, "47": 1.2909944487358056, "48": 1.2909944487358056, "49": 1.2909944487358056, "50": 1.2909944487358056, "51": 1.2909944487358056, "52": 1.2909944487358056, "53": 1.2909944487358056, "54": 1.2909944487358056, "55": 1.2909944487358056, "56": 1.2909944487358056, "57": 1.2909944487358056, "58": 1.2909944487358056, "59": 1.2909944487358056, "60": 1.2909944487358056, "61": 1.2909944487358056, "62": 1.2909944487358056, "63": 1.2909944487358056, "64": 1.2909944487358056, "65": 1.2909944487358056, "66": 1.2909944487358056, "67": 1.2909944487358056, "68": 1.2909944487358056, "69": 1.2909944487358056, "70": 1.2909944487358056, "71": 1.2909944487358056, "72": 1.2909944487358056, "73": 1.2909944487358056, "74": 1.2909944487358056, "75": 1.2909944487358056, "76": 1.2909944487358056, "77": 1.2909944487358056, "78": 1.2909944487358056, "79": 1.2909944487358056, "80": 1.2909944487358056, "81": 1.2909944487358056, "82": 1.2909944487358056, "83": 1.2909944487358056, "84": 1.2909944487358056, "85": 1.2909944487358056, "86": 1.2909944487358056, "87": 1.2909944487358056, "88": 1.2909944487358056, "89": 1.2909944487358056, "90": 1.2909944487358056, "91": 1.2909944487358056, "92": 1.2909944487358056, "93": 1.2909944487358056, "94": 1.2909944487358056, "95": 1.2909944487358056, "96": 1.2909944487358056, "97": 1.2909944487358056, "98": 1.2909944487358056, "99": 1.2909944487358056, "100": 1.2909944487358056, "101": 1.2909944487358056, "102": 1.2909944487358056, "103": 1.2909944487358056, "104": 1.2909944487358056, "105": 1.2909944487358056, "106": 1.2909944487358056, "107": 1.2909944487358056, "108": 1.2909944487358056, "109": 1.2909944487358056, "110": 1.2909944487358056, "111": 1.2909944487358056, "112": 1.2909944487358056, "113": 1.2909944487358056, "114": 1.2909944487358056, "115": 1.2909944487358056, "116": 1.2909944487358056, "117": 1.2909944487358056, "118": 1.2909944487358056, "119": 1.2909944487358056, "120": 1.2909944487358056, "121": 1.2909944487358056, "122": 1.2909944487358056, "123": 1.2909944487358056, "124": 1.2909944487358056, "125": 1.2909944487358056, "126": 1.2909944487358056, "127": 1.2909944487358056, "128": 1.2909944487358056, "129": 1.2909944487358056, "130": 1.2909944487358056, "131": 1.2909944487358056, "132": 1.2909944487358056, "133": 1.2909944487358056, "134": 1.2909944487358056, "135": 1.2909944487358056, "136": 1.2909944487358056, "137": 1.2909944487358056, "138": 1.2909944487358056, "139": 1.2909944487358056, "140": 1.2909944487358056, "141": 1.2909944487358056, "142": 1.2909944487358056, "143": 1.2909944487358056, "144": 1.2909944487358056, "145": 1.2909944487358056, "146": 1.2909944487358056, "147": 1.2909944487358056, "148": 1.2909944487358056, "149": 1.2909944487358056}}}, "x_name": "Index binned", "plot_shape": {"y0": 115.52778022774939, "y1": 430.4722197722506}}}, {"type": "evidently:metric_result:ColumnDataDriftMetrics", "column_name": "area", "column_type": "num", "stattest_name": "K-S p_value", "stattest_threshold": 0.05, "drift_score": 0.03958772716902705, "drift_detected": true, "current": {"type": "evidently:metric_result:DriftStatsField", "distribution": {"type": "evidently:metric_result:Distribution", "x": [-1.6145297288894653, -1.1951051577925682, -0.7756805866956711, -0.35625601559877396, 0.06316855549812317, 0.4825931265950203, 0.9020176976919174, 1.3214422687888145, 1.7408668398857117, 2.160291410982609, 2.579715982079506, 2.999140553176403, 3.4185651242733, 3.8379896953701973, 4.257414266467094, 4.6768388375639915, 5.096263408660889], "y": [28, 86, 135, 69, 78, 65, 86, 23, 10, 9, 4, 1, 4, 0, 0, 2]}, "characteristic_examples": null, "characteristic_words": null, "small_distribution": {"type": "evidently:metric_result:DistributionIncluded", "x": [-1.6145297288894653, -0.94345041513443, -0.2723711013793946, 0.3987082123756407, 1.0697875261306762, 1.7408668398857117, 2.4119461536407467, 3.0830254673957826, 3.7541047811508177, 4.425184094905853, 5.096263408660889], "y": [0.1812999807517219, 0.4942287146519542, 0.28809312009862664, 0.21855340145413046, 0.2334547697350939, 0.037253420702408634, 0.019868491041284575, 0.012417806900802878, 0.0, 0.004967122760321144]}, "correlations": null}, "reference": {"type": "evidently:metric_result:DriftStatsField", "distribution": {"type": "evidently:metric_result:Distribution", "x": [-1.6145297288894653, -1.1951051577925682, -0.7756805866956711, -0.35625601559877396, 0.06316855549812317, 0.4825931265950203, 0.9020176976919174, 1.3214422687888145, 1.7408668398857117, 2.160291410982609, 2.579715982079506, 2.999140553176403, 3.4185651242733, 3.8379896953701973, 4.257414266467094, 4.6768388375639915, 5.096263408660889], "y": [28, 86, 135, 69, 78, 65, 31, 23, 10, 9, 4, 1, 4, 0, 0, 2]}, "characteristic_examples": null, "characteristic_words": null, "small_distribution": {"type": "evidently:metric_result:DistributionIncluded", "x": [-1.6145297288894653, -0.94345041513443, -0.2723711013793946, 0.3987082123756407, 1.0697875261306762, 1.7408668398857117, 2.4119461536407467, 3.0830254673957826, 3.7541047811508177, 4.425184094905853, 5.096263408660889], "y": [0.1995963090844645, 0.5441050069562798, 0.3171667377232587, 0.2406092493072996, 0.10663364457937141, 0.04101294022283519, 0.021873568118845405, 0.013670980074278397, 0.0, 0.005468392029711351]}, "correlations": null}, "scatter": {"type": "evidently:metric_result:ScatterAggField", "scatter": {"current (mean)": {"per": {"0": 0, "1": 1, "2": 2, "3": 3, "4": 4, "5": 5, "6": 6, "7": 7, "8": 8, "9": 9, "10": 10, "11": 11, "12": 12, "13": 13, "14": 14, "15": 15, "16": 16, "17": 17, "18": 18, "19": 19, "20": 20, "21": 21, "22": 22, "23": 23, "24": 24, "25": 25, "26": 26, "27": 27, "28": 28, "29": 29, "30": 30, "31": 31, "32": 32, "33": 33, "34": 34, "35": 35, "36": 36, "37": 37, "38": 38, "39": 39, "40": 40, "41": 41, "42": 42, "43": 43, "44": 44, "45": 45, "46": 46, "47": 47, "48": 48, "49": 49, "50": 50, "51": 51, "52": 52, "53": 53, "54": 54, "55": 55, "56": 56, "57": 57, "58": 58, "59": 59, "60": 60, "61": 61, "62": 62, "63": 63, "64": 64, "65": 65, "66": 66, "67": 67, "68": 68, "69": 69, "70": 70, "71": 71, "72": 72, "73": 73, "74": 74, "75": 75, "76": 76, "77": 77, "78": 78, "79": 79, "80": 80, "81": 81, "82": 82, "83": 83, "84": 84, "85": 85, "86": 86, "87": 87, "88": 88, "89": 89, "90": 90, "91": 91, "92": 92, "93": 93, "94": 94, "95": 95, "96": 96, "97": 97, "98": 98, "99": 99, "100": 100, "101": 101, "102": 102, "103": 103, "104": 104, "105": 105, "106": 106, "107": 107, "108": 108, "109": 109, "110": 110, "111": 111, "112": 112, "113": 113, "114": 114, "115": 115, "116": 116, "117": 117, "118": 118, "119": 119, "120": 120, "121": 121, "122": 122, "123": 123, "124": 124, "125": 125, "126": 126, "127": 127, "128": 128, "129": 129, "130": 130, "131": 131, "132": 132, "133": 133, "134": 134, "135": 135, "136": 136, "137": 137, "138": 138, "139": 139, "140": 140, "141": 141, "142": 142, "143": 143, "144": 144, "145": 145, "146": 146, "147": 147, "148": 148, "149": 149}, "mean": {"0": 1.526398092508316, "1": 2.2020896673202515, "2": 1.4353065639734268, "3": 0.37449392676353455, "4": 0.6362379342317581, "5": 0.4015907943248749, "6": 1.1084148436784744, "7": 0.8443647623062134, "8": 0.47019768320024014, "9": 0.9085900485515594, "10": 0.5520647466182709, "11": 0.46097323298454285, "12": 0.5653249174356461, "13": 0.2937799322899082, "14": 1.5586836636066437, "15": 0.7930537164211273, "16": 2.3467982709407806, "17": 0.863390177488327, "18": -0.07865753211081028, "19": 0.4632793441414833, "20": 0.680054098367691, "21": 0.23497401177883148, "22": 0.823033170774579, "23": 0.1727089285850525, "24": 0.8530126810073853, "25": 0.38602451980113983, "26": 0.14618860557675362, "27": 0.48714764416217804, "28": 0.9360328018665314, "29": 0.3964020162820816, "30": 0.7774874269962311, "31": 1.7506677359342575, "32": 0.8055067509412766, "33": 0.2764840768650174, "34": 0.09199492447078228, "35": 0.8253393173217773, "36": 0.5878095235675573, "37": 0.21836999827064574, "38": -0.24815694987773895, "39": 0.028230875730514526, "40": 0.591845229268074, "41": 0.5716667175292969, "42": 0.6880101636052132, "43": 0.7722986917942762, "44": 0.4880700707435608, "45": 0.2868615984916687, "46": 0.33528997749090195, "47": 0.8022781908512115, "48": 0.38717758655548096, "49": 0.0036707445979118347, "50": -0.28447825461626053, "51": -0.08442282676696777, "52": 0.7649190947413445, "53": -0.4239981770515442, "54": 0.4744639992713928, "55": 0.7385141104459763, "56": 0.8357168470975012, "57": 0.2784442752599716, "58": -0.3617330864071846, "59": -0.4856867343187332, "60": -0.7854816168546677, "61": 0.2303617838770151, "62": -0.5248906798660755, "63": 0.3658460006117821, "64": 0.2361270636320114, "65": -0.7162981778383255, "66": -0.34847292862832546, "67": -0.6165587101131678, "68": -0.2934721112251282, "69": 0.4517487958073616, "70": -0.3698045015335083, "71": 0.2426994889974594, "72": -0.4784224918112159, "73": -0.8209957629442215, "74": 0.05048486590385437, "75": -0.7331328094005585, "76": 0.0020564422011375427, "77": 0.013932950794696808, "78": -0.42457469180226326, "79": -0.27329360134899616, "80": -0.4372583329677582, "81": -0.237779438495636, "82": -0.09595340490341187, "83": -0.5760864168405533, "84": -0.3940186947584152, "85": -0.102641137316823, "86": -1.0621000528335571, "87": -0.6471147425472736, "88": 0.5458382368087769, "89": -0.469543918967247, "90": -0.335328072309494, "91": -0.550257932394743, "92": -0.40497272461652756, "93": -0.5698599144816399, "94": -0.9025169312953949, "95": -0.5133601129055023, "96": -0.5041356533765793, "97": -0.8280293941497803, "98": -0.24308347702026367, "99": -0.06828003376722336, "100": 1.2953254356980324, "101": -0.5969567578285933, "102": -0.8558180928230286, "103": -0.8321804329752922, "104": -0.5825435556471348, "105": -0.49145202711224556, "106": -1.0921948105096817, "107": -0.7041910737752914, "108": -0.37245650589466095, "109": -0.4781918600201607, "110": -0.6443474292755127, "111": -0.7548102885484695, "112": -0.5369977876543999, "113": 0.16855792701244354, "114": -0.9056301862001419, "115": -0.26429973915219307, "116": -0.6886247992515564, "117": -0.5005611795932055, "118": -0.18104901909828186, "119": -0.29197312518954277, "120": -0.5369977653026581, "121": -0.29197312146425247, "122": -0.5894618732854724, "123": -0.368074893951416, "124": -0.8115407079458237, "125": -0.9100117683410645, "126": -0.7964356392621994, "127": -0.754349060356617, "128": -0.8062366470694542, "129": -0.694390095770359, "130": -0.4618184417486191, "131": -1.0011033117771149, "132": -0.6240536142140627, "133": -1.0195522457361221, "134": -1.0196675211191177, "135": -0.9999502450227737, "136": 0.8184209614992142, "137": 1.2911744117736816, "138": 1.2911744117736816, "139": 1.2911744117736816, "140": 1.2911744117736816, "141": 1.2911744117736816, "142": 1.2911744117736816, "143": 1.2911744117736816, "144": 1.2911744117736816, "145": 1.2911744117736816, "146": 1.2911744117736816, "147": 1.2911744117736816, "148": 1.2911744117736816, "149": 1.2911744117736816}, "std": {"0": 0.5650811431245503, "1": 1.944813528886386, "2": 1.5940989625255135, "3": 0.8330522381839394, "4": 0.7352033543658859, "5": 0.8600176069318263, "6": 0.691355968180247, "7": 0.4893253004392497, "8": 0.44922887398733136, "9": 0.6616709742689956, "10": 0.11281119632680482, "11": 0.13836687803268433, "12": 0.6828886649419398, "13": 0.19601972335658502, "14": 1.0588857431958296, "15": 0.6218817234305231, "16": 1.1277824397231633, "17": 1.6177043116425898, "18": 0.5344350758955237, "19": 0.17263541578913144, "20": 1.2683629393577576, "21": 1.0044427415918111, "22": 0.6897865178623054, "23": 0.6294467276732783, "24": 0.6256331643056557, "25": 0.26386290899208925, "26": 0.36166805457894596, "27": 0.9896151875140321, "28": 1.0335509783737786, "29": 0.7202760027186172, "30": 0.24063591706107518, "31": 2.0507511969155745, "32": 1.4169066745637668, "33": 0.4479643315331358, "34": 0.34196911199411373, "35": 1.1493985219930787, "36": 1.2621983180066627, "37": 0.47862048594565887, "38": 0.6234688750926963, "39": 1.205638050233138, "40": 0.15576519820057388, "41": 0.6129349397242922, "42": 1.195140525320073, "43": 1.2717128798182302, "44": 1.0418676182717002, "45": 1.0003141930164727, "46": 1.8298030888750467, "47": 1.3992522437715402, "48": 0.7966482352603207, "49": 0.9781409034083727, "50": 0.2810898712691035, "51": 0.6725358867350345, "52": 2.002024121088792, "53": 0.29897998487223854, "54": 0.4627843035679054, "55": 1.1586547137438932, "56": 1.036622630820405, "57": 1.2491285226926208, "58": 0.4117447625106459, "59": 0.4226401550957049, "60": 0.2785566026852213, "61": 0.9336165819360146, "62": 0.3296022996344721, "63": 1.2845607367816436, "64": 0.9444028675890677, "65": 0.1592929203002804, "66": 0.4658959941011283, "67": 0.6195265652532779, "68": 0.6073061846290396, "69": 1.4188783484610112, "70": 0.7896354463683246, "71": 0.9860109367505998, "72": 0.7283383036247912, "73": 0.45803348070795524, "74": 0.6725635564757445, "75": 0.4731212994124878, "76": 0.9870923815066247, "77": 0.4618898393702745, "78": 0.4303978078793738, "79": 0.5626294166082602, "80": 0.4061970264982373, "81": 0.6007180771902371, "82": 0.7208701074072844, "83": 0.5156042056729633, "84": 1.2044061686509806, "85": 0.7925865139529534, "86": 0.41265756131563314, "87": 0.34062644782381424, "88": 1.199472471555791, "89": 0.888596453502212, "90": 0.5010267035417167, "91": 0.47212306228827994, "92": 0.4468449925576742, "93": 0.6366156798312929, "94": 0.3713984117574953, "95": 0.2937468258629179, "96": 0.17792984297264905, "97": 0.4783699273439439, "98": 0.8669382043823645, "99": 0.9114832569186978, "100": 1.9076823049819824, "101": 0.6941043585819714, "102": 0.3895126556819855, "103": 0.5979833144494916, "104": 0.3318535347482629, "105": 0.22101834707390275, "106": 0.2189432578969601, "107": 0.4580114950511494, "108": 0.5384183874967178, "109": 0.7134591948000267, "110": 0.36294335934694316, "111": 0.16464903321976979, "112": 0.9746171249210827, "113": 1.1655581355712845, "114": 0.2910980443255434, "115": 1.208934164290828, "116": 0.29490324225394343, "117": 0.45506838132011784, "118": 1.0437997387982507, "119": 0.501615661550606, "120": 0.8216315250829032, "121": 0.6493954228070705, "122": 0.5216153372201294, "123": 0.8062423567823055, "124": 0.4341160285293319, "125": 0.32277637754030236, "126": 0.22024195072907327, "127": 0.304302256332134, "128": 0.31009308236498073, "129": 0.3793166903672746, "130": 1.1149490429189155, "131": 0.3636542931772222, "132": 0.6374380147880082, "133": 0.1835644029455686, "134": 0.4014830299632194, "135": 0.23080740290151489, "136": 0.945506900548935, "137": 0.0, "138": 0.0, "139": 0.0, "140": 0.0, "141": 0.0, "142": 0.0, "143": 0.0, "144": 0.0, "145": 0.0, "146": 0.0, "147": 0.0, "148": 0.0, "149": 0.0}}}, "x_name": "Index binned", "plot_shape": {"y0": -1.0009186972459163, "y1": 1.0009187004086748}}}, {"type": "evidently:metric_result:ColumnDataDriftMetrics", "column_name": "bedrooms", "column_type": "num", "stattest_name": "K-S p_value", "stattest_threshold": 0.05, "drift_score": 0.08435116369069741, "drift_detected": false, "current": {"type": "evidently:metric_result:DriftStatsField", "distribution": {"type": "evidently:metric_result:Distribution", "x": [-2.665003776550293, -2.1806676728384837, -1.696331569126674, -1.2119954654148648, -0.7276593617030553, -0.24332325799124588, 0.24101284572056336, 0.725348949432373, 1.2096850531441823, 1.6940211568559915, 2.178357260567801, 2.662693364279611, 3.1470294679914197, 3.6313655717032294, 4.115701675415039], "y": [2, 0, 136, 0, 0, 300, 0, 55, 95, 0, 0, 10, 0, 2]}, "characteristic_examples": null, "characteristic_words": null, "small_distribution": {"type": "evidently:metric_result:DistributionIncluded", "x": [-2.665003776550293, -1.9869332313537598, -1.3088626861572266, -0.6307921409606934, 0.047278404235839844, 0.725348949432373, 1.4034194946289062, 2.0814900398254395, 2.7595605850219727, 3.437631130218506, 4.115701675415039], "y": [0.00491590935035704, 0.0, 0.33428183582427873, 0.737386402553556, 0.0, 0.368693201276778, 0.0, 0.024579546751785197, 0.0, 0.00491590935035704]}, "correlations": null}, "reference": {"type": "evidently:metric_result:DriftStatsField", "distribution": {"type": "evidently:metric_result:Distribution", "x": [-2.665003776550293, -2.1806676728384837, -1.696331569126674, -1.2119954654148648, -0.7276593617030553, -0.24332325799124588, 0.24101284572056336, 0.725348949432373, 1.2096850531441823, 1.6940211568559915, 2.178357260567801, 2.662693364279611, 3.1470294679914197, 3.6313655717032294, 4.115701675415039], "y": [2, 0, 136, 0, 0, 300, 0, 0, 95, 0, 0, 10, 0, 2]}, "characteristic_examples": null, "characteristic_words": null, "small_distribution": {"type": "evidently:metric_result:DistributionIncluded", "x": [-2.665003776550293, -1.9869332313537598, -1.3088626861572266, -0.6307921409606934, 0.047278404235839844, 0.725348949432373, 1.4034194946289062, 2.0814900398254395, 2.7595605850219727, 3.437631130218506, 4.115701675415039], "y": [0.0054120102939710524, 0.0, 0.3680166999900316, 0.811801544095658, 0.0, 0.25707048896362505, 0.0, 0.027060051469855264, 0.0, 0.0054120102939710524]}, "correlations": null}, "scatter": {"type": "evidently:metric_result:ScatterAggField", "scatter": {"current (mean)": {"per": {"0": 0, "1": 1, "2": 2, "3": 3, "4": 4, "5": 5, "6": 6, "7": 7, "8": 8, "9": 9, "10": 10, "11": 11, "12": 12, "13": 13, "14": 14, "15": 15, "16": 16, "17": 17, "18": 18, "19": 19, "20": 20, "21": 21, "22": 22, "23": 23, "24": 24, "25": 25, "26": 26, "27": 27, "28": 28, "29": 29, "30": 30, "31": 31, "32": 32, "33": 33, "34": 34, "35": 35, "36": 36, "37": 37, "38": 38, "39": 39, "40": 40, "41": 41, "42": 42, "43": 43, "44": 44, "45": 45, "46": 46, "47": 47, "48": 48, "49": 49, "50": 50, "51": 51, "52": 52, "53": 53, "54": 54, "55": 55, "56": 56, "57": 57, "58": 58, "59": 59, "60": 60, "61": 61, "62": 62, "63": 63, "64": 64, "65": 65, "66": 66, "67": 67, "68": 68, "69": 69, "70": 70, "71": 71, "72": 72, "73": 73, "74": 74, "75": 75, "76": 76, "77": 77, "78": 78, "79": 79, "80": 80, "81": 81, "82": 82, "83": 83, "84": 84, "85": 85, "86": 86, "87": 87, "88": 88, "89": 89, "90": 90, "91": 91, "92": 92, "93": 93, "94": 94, "95": 95, "96": 96, "97": 97, "98": 98, "99": 99, "100": 100, "101": 101, "102": 102, "103": 103, "104": 104, "105": 105, "106": 106, "107": 107, "108": 108, "109": 109, "110": 110, "111": 111, "112": 112, "113": 113, "114": 114, "115": 115, "116": 116, "117": 117, "118": 118, "119": 119, "120": 120, "121": 121, "122": 122, "123": 123, "124": 124, "125": 125, "126": 126, "127": 127, "128": 128, "129": 129, "130": 130, "131": 131, "132": 132, "133": 133, "134": 134, "135": 135, "136": 136, "137": 137, "138": 138, "139": 139, "140": 140, "141": 141, "142": 142, "143": 143, "144": 144, "145": 145, "146": 146, "147": 147, "148": 148, "149": 149}, "mean": {"0": 1.0643841093406081, "1": 1.4034193521365523, "2": 0.7253488432615995, "3": 1.0643841093406081, "4": 0.38631357718259096, "5": 0.04727831110358238, "6": 0.38631357718259096, "7": 1.0643840860575438, "8": 1.0643840860575438, "9": 0.7253488432615995, "10": 0.38631357718259096, "11": 0.38631357718259096, "12": 0.04727831110358238, "13": 0.38631357718259096, "14": 1.0643841093406081, "15": 0.3863135939463973, "16": -0.29175693821161985, "17": 0.7253488432615995, "18": 0.047278327867388725, "19": 0.04727831110358238, "20": 0.04727831110358238, "21": 0.04727831110358238, "22": 0.38631357066333294, "23": 0.38631357718259096, "24": 0.38631357718259096, "25": 0.04727831110358238, "26": 0.38631357718259096, "27": 0.7253488432615995, "28": 0.7253489028662443, "29": 0.38631357718259096, "30": 0.7253488432615995, "31": 0.04727831110358238, "32": 0.38631357718259096, "33": 0.04727831110358238, "34": 0.7253488432615995, "35": 1.4034193521365523, "36": 0.047278327867388725, "37": 0.7253488432615995, "38": 0.7253488199785352, "39": 0.38631357718259096, "40": 0.7253488432615995, "41": -0.29175693821161985, "42": 0.7253488432615995, "43": 0.7253488432615995, "44": 0.04727831110358238, "45": 0.38631357718259096, "46": -0.29175693821161985, "47": -0.2917569214478135, "48": 0.047278327867388725, "49": 0.04727831110358238, "50": 0.047278327867388725, "51": -0.29175693821161985, "52": 0.04727831110358238, "53": 0.3863135939463973, "54": -0.29175693821161985, "55": 0.3863135939463973, "56": -0.9698274368420243, "57": 0.047278327867388725, "58": 0.04727831110358238, "59": 0.047278327867388725, "60": 0.04727831110358238, "61": 0.38631357718259096, "62": 0.047278327867388725, "63": -0.2917569214478135, "64": -0.29175693821161985, "65": -0.29175693821161985, "66": -0.29175693821161985, "67": 1.0643840860575438, "68": 0.3863135939463973, "69": -0.9698274368420243, "70": -0.2917569214478135, "71": -0.29175693821161985, "72": 0.047278327867388725, "73": 0.3863135939463973, "74": 0.04727831110358238, "75": 0.04727831110358238, "76": 0.04727831110358238, "77": 0.047278327867388725, "78": -0.6307921875268221, "79": 0.7253488432615995, "80": 0.04727831110358238, "81": 0.7253488432615995, "82": -0.29175693821161985, "83": -0.2917569214478135, "84": 0.3863135939463973, "85": 0.0472783213481307, "86": -0.6307921875268221, "87": -0.9698274368420243, "88": -0.6307921875268221, "89": 0.7253488367423415, "90": -0.9698274368420243, "91": -0.9698274368420243, "92": -0.9698274368420243, "93": -0.6307921875268221, "94": 0.04727831110358238, "95": -0.2917569214478135, "96": -0.6307921875268221, "97": 0.38631357718259096, "98": 1.0643841521814466, "99": -0.9698274368420243, "100": -0.6307921875268221, "101": -0.29175693821161985, "102": -0.6307921875268221, "103": -0.29175693821161985, "104": 0.3863135939463973, "105": -0.9698274368420243, "106": -0.29175693821161985, "107": 0.04727834463119507, "108": 0.3863135939463973, "109": -0.6307921875268221, "110": 0.047278327867388725, "111": -1.308862709440291, "112": -0.6307921875268221, "113": -0.29175693821161985, "114": -0.29175693821161985, "115": -0.9698274368420243, "116": -0.6307921875268221, "117": -0.6307921875268221, "118": 0.04727834463119507, "119": 0.047278327867388725, "120": -0.29175693821161985, "121": -0.6307921707630157, "122": 0.047278327867388725, "123": -0.29175693821161985, "124": -0.9698274368420243, "125": -0.29175693821161985, "126": -0.9698274368420243, "127": -0.6307921875268221, "128": -0.29175693821161985, "129": -1.3088626861572266, "130": -0.2917569214478135, "131": -1.3088626861572266, "132": -0.6307922108098865, "133": -0.2917569214478135, "134": 0.0472783213481307, "135": -0.6307921875268221, "136": 0.7618195777758956, "137": 1.0, "138": 1.0, "139": 1.0, "140": 1.0, "141": 1.0, "142": 1.0, "143": 1.0, "144": 1.0, "145": 1.0, "146": 1.0, "147": 1.0, "148": 1.0, "149": 1.0}, "std": {"0": 0.6780705321580172, "1": 1.1072845042486448, "2": 0.782968408541968, "3": 0.6780705321580172, "4": 0.6780705321580172, "5": 0.0, "6": 0.6780705321580172, "7": 1.2984061763870904, "8": 1.2984061763870904, "9": 0.782968408541968, "10": 0.6780705321580172, "11": 0.6780705321580172, "12": 0.0, "13": 0.6780705321580172, "14": 0.6780705321580172, "15": 1.2984061877356619, "16": 0.6780704986304045, "17": 0.782968408541968, "18": 1.1072845148945485, "19": 0.0, "20": 0.0, "21": 0.0, "22": 1.7064400190306086, "23": 0.6780705321580172, "24": 0.6780705321580172, "25": 0.0, "26": 0.6780705321580172, "27": 0.782968408541968, "28": 2.3489052887159603, "29": 0.6780705321580172, "30": 0.782968408541968, "31": 0.0, "32": 0.6780705321580172, "33": 0.0, "34": 0.782968408541968, "35": 1.1072845042486448, "36": 1.1072845148945485, "37": 0.782968408541968, "38": 1.3561410177499056, "39": 0.6780705321580172, "40": 0.782968408541968, "41": 0.6780704986304045, "42": 0.782968408541968, "43": 0.782968408541968, "44": 0.0, "45": 0.6780705321580172, "46": 0.6780704986304045, "47": 1.2984061818992536, "48": 1.1072845148945485, "49": 0.0, "50": 1.1072845148945485, "51": 0.6780704986304045, "52": 0.0, "53": 1.2984061877356619, "54": 0.6780704986304045, "55": 1.2984061877356619, "56": 0.6780704986304045, "57": 1.1072845148945485, "58": 0.0, "59": 1.1072845148945485, "60": 0.0, "61": 0.6780705321580172, "62": 1.1072845148945485, "63": 1.2984061818992536, "64": 0.6780704986304045, "65": 0.6780704986304045, "66": 0.6780704986304045, "67": 1.2984061763870904, "68": 1.2984061877356616, "69": 0.6780704986304045, "70": 1.2984061818992538, "71": 0.6780704986304045, "72": 1.1072845148945485, "73": 1.2984061877356619, "74": 0.0, "75": 0.0, "76": 0.0, "77": 1.1072845148945485, "78": 0.7829683698276155, "79": 0.782968408541968, "80": 0.0, "81": 0.782968408541968, "82": 0.6780704986304045, "83": 1.2984061818992536, "84": 1.2984061877356619, "85": 1.917873010133716, "86": 0.7829683698276155, "87": 0.6780704986304045, "88": 0.7829683698276155, "89": 1.750770523694322, "90": 0.6780704986304045, "91": 0.6780704986304045, "92": 0.6780704986304045, "93": 0.7829683698276155, "94": 0.0, "95": 1.2984061818992538, "96": 0.7829683698276155, "97": 0.6780705321580172, "98": 2.0342116821557283, "99": 0.6780704986304045, "100": 0.7829683698276155, "101": 0.6780704986304045, "102": 0.7829683698276155, "103": 0.6780704986304045, "104": 1.2984061877356619, "105": 0.6780704986304045, "106": 0.6780704986304045, "107": 1.5659367783695837, "108": 1.2984061877356616, "109": 0.7829683698276155, "110": 1.1072845148945485, "111": 1.1072845255404524, "112": 0.7829683698276155, "113": 0.6780704986304045, "114": 0.6780704986304045, "115": 0.6780704986304045, "116": 0.7829683698276155, "117": 0.7829683698276155, "118": 1.5659367783695837, "119": 1.1072845148945485, "120": 0.6780704986304045, "121": 1.3561410307884216, "122": 1.1072845148945485, "123": 0.6780704986304045, "124": 0.6780704986304045, "125": 0.6780704986304045, "126": 0.6780704986304045, "127": 0.7829683698276155, "128": 0.6780704986304045, "129": 0.0, "130": 1.2984061818992538, "131": 0.0, "132": 1.3561410438269377, "133": 1.2984061818992536, "134": 1.917873010133716, "135": 0.7829683698276155, "136": 0.47636084444820875, "137": 0.0, "138": 0.0, "139": 0.0, "140": 0.0, "141": 0.0, "142": 0.0, "143": 0.0, "144": 0.0, "145": 0.0, "146": 0.0, "147": 0.0, "148": 0.0, "149": 0.0}}}, "x_name": "Index binned", "plot_shape": {"y0": -1.0009186703796578, "y1": 1.0009186995257824}}}], "tests": [{"type": "evidently:test:TestNumberOfDriftedColumns", "is_critical": true, "feature_importance": false}, {"lt": 0.3, "type": "evidently:test:TestShareOfDriftedColumns", "is_critical": true, "feature_importance": false}, {"type": "evidently:test:TestColumnDrift", "is_critical": true, "column_name": {"type": "evidently:base:ColumnName", "name": "mainroad", "display_name": "mainroad", "dataset": "main"}, "stattest": null, "stattest_threshold": null}, {"type": "evidently:test:TestColumnDrift", "is_critical": true, "column_name": {"type": "evidently:base:ColumnName", "name": "house_id", "display_name": "house_id", "dataset": "main"}, "stattest": null, "stattest_threshold": null}, {"type": "evidently:test:TestColumnDrift", "is_critical": true, "column_name": {"type": "evidently:base:ColumnName", "name": "area", "display_name": "area", "dataset": "main"}, "stattest": null, "stattest_threshold": null}, {"type": "evidently:test:TestColumnDrift", "is_critical": true, "column_name": {"type": "evidently:base:ColumnName", "name": "bedrooms", "display_name": "bedrooms", "dataset": "main"}, "stattest": null, "stattest_threshold": null}], "test_results": [{"type": "evidently:metric_result:TestResult", "name": "Number of Drifted Features", "description": "The drift is detected for 3 out of 4 features. The test threshold is lt=1.", "status": "FAIL", "group": "data_drift", "parameters": {"type": "evidently:test_parameters:ColumnsDriftParameters", "condition": {"lt": 1}, "features": {"area": {"type": "evidently:test_parameters:ColumnDriftParameter", "stattest": "K-S p_value", "score": 0.04, "threshold": 0.05, "detected": true}, "bedrooms": {"type": "evidently:test_parameters:ColumnDriftParameter", "stattest": "K-S p_value", "score": 0.084, "threshold": 0.05, "detected": false}, "house_id": {"type": "evidently:test_parameters:ColumnDriftParameter", "stattest": "K-S p_value", "score": 0.015, "threshold": 0.05, "detected": true}, "mainroad": {"type": "evidently:test_parameters:ColumnDriftParameter", "stattest": "chi-square p_value", "score": 0.0, "threshold": 0.05, "detected": true}}}}, {"type": "evidently:metric_result:TestResult", "name": "Share of Drifted Columns", "description": "The drift is detected for 75% features (3 out of 4). The test threshold is lt=0.3", "status": "FAIL", "group": "data_drift", "parameters": {"type": "evidently:test_parameters:ColumnsDriftParameters", "condition": {"lt": 0.3}, "features": {"area": {"type": "evidently:test_parameters:ColumnDriftParameter", "stattest": "K-S p_value", "score": 0.04, "threshold": 0.05, "detected": true}, "bedrooms": {"type": "evidently:test_parameters:ColumnDriftParameter", "stattest": "K-S p_value", "score": 0.084, "threshold": 0.05, "detected": false}, "house_id": {"type": "evidently:test_parameters:ColumnDriftParameter", "stattest": "K-S p_value", "score": 0.015, "threshold": 0.05, "detected": true}, "mainroad": {"type": "evidently:test_parameters:ColumnDriftParameter", "stattest": "chi-square p_value", "score": 0.0, "threshold": 0.05, "detected": true}}}}, {"type": "evidently:metric_result:TestResult", "name": "Drift per Column", "description": "The drift score for the feature **mainroad** is 0. The drift detection method is chi-square p_value. The drift detection threshold is 0.05.", "status": "FAIL", "group": "data_drift", "parameters": {"type": "evidently:test_parameters:ColumnDriftParameter", "stattest": "chi-square p_value", "score": 0.0, "threshold": 0.05, "detected": true, "column_name": "mainroad"}}, {"type": "evidently:metric_result:TestResult", "name": "Drift per Column", "description": "The drift score for the feature **house_id** is 0.015. The drift detection method is K-S p_value. The drift detection threshold is 0.05.", "status": "FAIL", "group": "data_drift", "parameters": {"type": "evidently:test_parameters:ColumnDriftParameter", "stattest": "K-S p_value", "score": 0.015, "threshold": 0.05, "detected": true, "column_name": "house_id"}}, {"type": "evidently:metric_result:TestResult", "name": "Drift per Column", "description": "The drift score for the feature **area** is 0.04. The drift detection method is K-S p_value. The drift detection threshold is 0.05.", "status": "FAIL", "group": "data_drift", "parameters": {"type": "evidently:test_parameters:ColumnDriftParameter", "stattest": "K-S p_value", "score": 0.04, "threshold": 0.05, "detected": true, "column_name": "area"}}, {"type": "evidently:metric_result:TestResult", "name": "Drift per Column", "description": "The drift score for the feature **bedrooms** is 0.084. The drift detection method is K-S p_value. The drift detection threshold is 0.05.", "status": "SUCCESS", "group": "data_drift", "parameters": {"type": "evidently:test_parameters:ColumnDriftParameter", "stattest": "K-S p_value", "score": 0.084, "threshold": 0.05, "detected": false, "column_name": "bedrooms"}}], "options": {"color": null, "render": null, "data_definition": null}, "data_definition": {"columns": {"house_id": {"column_name": "house_id", "column_type": "num"}, "bedrooms": {"column_name": "bedrooms", "column_type": "num"}, "area": {"column_name": "area", "column_type": "num"}, "mainroad": {"column_name": "mainroad", "column_type": "cat"}}, "target": null, "prediction_columns": null, "id_column": null, "datetime_column": null, "embeddings": null, "user_id": null, "item_id": null, "task": null, "classification_labels": null, "reference_present": true, "recommendations_type": "score"}, "run_metadata": {"descriptors": {}}}, "metrics_ids": [], "test_ids": [0, 1, 2, 3, 4, 5], "options": {"color": null, "render": null, "data_definition": null}, "links": {"datasets": {"input": {"reference": null, "current": null, "additional": {}}, "output": {"reference": null, "current": null, "additional": {}}}, "computation_config_id": null, "task_id": null}}